{"assets":{"FBB5DEA59905EE30EF2803B0A74DF992":{"type":"texture","index":35,"assetRequest":{"type":"slide","state":"contents","slide":"D0A3ABB9-793E-4D80-BFEE-293C35AAEEB4"},"url":{"web":"assets/FBB5DEA59905EE30EF2803B0A74DF992.svg"},"width":1024,"height":768},"9CA919AABBCA48D7E777A73FD1D23962":{"type":"texture","index":40,"assetRequest":{"type":"slide","state":"contents","slide":"D0A3ABB9-793E-4D80-BFEE-293C35AAEEB4"},"url":{"web":"assets/9CA919AABBCA48D7E777A73FD1D23962.svg"},"width":784,"height":241},"15CA13132A771FE1DB043EB28E9335FD":{"type":"texture","index":37,"assetRequest":{"type":"slide","state":"contents","slide":"D0A3ABB9-793E-4D80-BFEE-293C35AAEEB4"},"url":{"web":"assets/15CA13132A771FE1DB043EB28E9335FD.svg"},"width":1040,"height":4},"5EF0F4E6B479EFE482472867F30CA441":{"type":"texture","index":42,"assetRequest":{"type":"slide","state":"contents","slide":"D0A3ABB9-793E-4D80-BFEE-293C35AAEEB4"},"url":{"web":"assets/5EF0F4E6B479EFE482472867F30CA441.svg"},"width":162,"height":26},"A8CE3FB2D25C34E000D23C6DCD563D2B":{"type":"texture","index":44,"assetRequest":{"type":"slide","state":"incoming","slide":"CE69DAAA-0412-4507-AB8A-1512288D1DCC"},"url":{"web":"assets/A8CE3FB2D25C34E000D23C6DCD563D2B.svg"},"width":1024,"height":768},"E3D145A6DF28781D6CA496FED15ABB33":{"type":"texture","index":39,"assetRequest":{"type":"slide","state":"contents","slide":"D0A3ABB9-793E-4D80-BFEE-293C35AAEEB4"},"url":{"web":"assets/E3D145A6DF28781D6CA496FED15ABB33.svg"},"width":314,"height":26},"3D8F234DC2E9CD7213DBB953CE7F5F57":{"type":"texture","index":41,"assetRequest":{"type":"slide","state":"contents","slide":"D0A3ABB9-793E-4D80-BFEE-293C35AAEEB4"},"url":{"web":"assets/3D8F234DC2E9CD7213DBB953CE7F5F57.svg"},"width":99,"height":25},"D8446BA52186825C4BB28690774F6E66":{"type":"texture","index":38,"assetRequest":{"type":"slide","state":"contents","slide":"D0A3ABB9-793E-4D80-BFEE-293C35AAEEB4"},"url":{"web":"assets/D8446BA52186825C4BB28690774F6E66.svg"},"width":346,"height":32},"15B89F6380020007C90634177F53413D":{"type":"texture","index":43,"assetRequest":{"type":"slide","state":"outgoing","slide":"D0A3ABB9-793E-4D80-BFEE-293C35AAEEB4"},"url":{"web":"assets/15B89F6380020007C90634177F53413D.svg"},"width":1024,"height":768},"26E1D36A86E033FA4AB154F481E23A88":{"type":"texture","index":36,"assetRequest":{"type":"slide","state":"contents","slide":"D0A3ABB9-793E-4D80-BFEE-293C35AAEEB4"},"url":{"web":"assets/26E1D36A86E033FA4AB154F481E23A88.svg"},"width":524,"height":70}},"events":[{"effects":[{"beginTime":0,"baseLayer":{"animations":[],"initialState":{"affineTransform":[1,0,0,1,0,0],"masksToBounds":false,"rotation":0,"scale":1,"position":{"pointX":307.6938996315002,"pointY":138.3412780761719},"width":606.2812328338623,"sublayerTransform":[1,0,0,0,0,1,0,0,0,0,1,0,0,0,0,1],"contentsRect":{"y":0,"x":0,"width":1,"height":1},"opacity":1,"edgeAntialiasingMask":251658240,"height":55.0000011920929,"hidden":false,"anchorPoint":{"pointX":0.5,"pointY":0.5}},"objectID":"B7C6A886-DC3C-46F7-B6D2-9A96B7DDDAD8","layers":[{"animations":[],"initialState":{"affineTransform":[1,0,0,1,0,0],"masksToBounds":false,"rotation":0,"scale":1,"position":{"pointX":507.4467167854309,"pointY":273.1587225198746},"width":606.2812328338623,"sublayerTransform":[1,0,0,0,0,1,0,0,0,0,1,-0.0004922987690640373,0,0,0,1],"contentsRect":{"y":0,"x":0,"width":1,"height":1},"opacity":1,"edgeAntialiasingMask":251658240,"height":55.0000011920929,"hidden":false,"anchorPoint":{"pointX":0.836982392500487,"pointY":4.966522119987615}},"layers":[{"animations":[{"timeOffset":0,"from":{"scalar":true},"beginTime":1e-100,"repeatCount":0,"fillMode":"both","property":"hidden","autoreverses":false,"duration":0.01,"to":{"scalar":false}}],"layers":[],"initialState":{"affineTransform":[1,0,0,1,0,0],"masksToBounds":false,"rotation":0,"scale":1,"position":{"pointX":173.4467167854309,"pointY":25.15872251987457},"width":346,"sublayerTransform":[1,0,0,0,0,1,0,0,0,0,1,0,0,0,0,1],"contentsRect":{"y":0,"x":0,"width":1,"height":1},"opacity":1,"edgeAntialiasingMask":0,"height":32,"hidden":true,"anchorPoint":{"pointX":0.5,"pointY":0.5}},"texture":"D8446BA52186825C4BB28690774F6E66"}]}]},"effects":[],"duration":0.01,"type":"buildIn","name":"apple:appear","objectID":"B7C6A886-DC3C-46F7-B6D2-9A96B7DDDAD8"}],"automaticPlay":false,"hyperlinks":[],"accessibility":[{"text":"ng-best-practices","targetRectangle":{"y":1.71030580997467,"x":7.553269386291504,"width":526.83125,"height":86}}],"baseLayer":{"animations":[],"initialState":{"affineTransform":[1,0,0,1,0,0],"masksToBounds":false,"rotation":0,"scale":1,"position":{"pointX":512,"pointY":384},"width":1024,"sublayerTransform":[1,0,0,0,0,1,0,0,0,0,1,0,0,0,0,1],"contentsRect":{"y":0,"x":0,"width":1,"height":1},"opacity":1,"edgeAntialiasingMask":251658240,"height":768,"hidden":false,"anchorPoint":{"pointX":0.5,"pointY":0.5}},"layers":[{"animations":[],"initialState":{"affineTransform":[1,0,0,1,0,0],"masksToBounds":false,"rotation":0,"scale":1,"position":{"pointX":512,"pointY":384},"width":1024,"sublayerTransform":[1,0,0,0,0,1,0,0,0,0,1,0,0,0,0,1],"contentsRect":{"y":0,"x":0,"width":1,"height":1},"opacity":1,"edgeAntialiasingMask":251658240,"height":768,"hidden":false,"anchorPoint":{"pointX":0.5,"pointY":0.5}},"layers":[{"animations":[],"initialState":{"affineTransform":[1,0,0,1,0,0],"masksToBounds":false,"rotation":0,"scale":1,"position":{"pointX":512,"pointY":384},"width":1024,"sublayerTransform":[1,0,0,0,0,1,0,0,0,0,1,0,0,0,0,1],"contentsRect":{"y":0,"x":0,"width":1,"height":1},"opacity":1,"edgeAntialiasingMask":251658240,"height":768,"hidden":false,"anchorPoint":{"pointX":0.5,"pointY":0.5}},"layers":[{"animations":[],"layers":[],"initialState":{"affineTransform":[1,0,0,1,0,0],"masksToBounds":false,"rotation":0,"scale":1,"position":{"pointX":512,"pointY":384},"width":1024,"sublayerTransform":[1,0,0,0,0,1,0,0,0,0,1,0,0,0,0,1],"contentsRect":{"y":0,"x":0,"width":1,"height":1},"opacity":1,"edgeAntialiasingMask":0,"height":768,"hidden":false,"anchorPoint":{"pointX":0.5,"pointY":0.5}},"texture":"FBB5DEA59905EE30EF2803B0A74DF992"}]}]},{"animations":[],"initialState":{"affineTransform":[1,0,0,1,0,0],"masksToBounds":false,"rotation":0,"scale":1,"position":{"pointX":512,"pointY":384},"width":1024,"sublayerTransform":[1,0,0,0,0,1,0,0,0,0,1,0,0,0,0,1],"contentsRect":{"y":0,"x":0,"width":1,"height":1},"opacity":1,"edgeAntialiasingMask":251658240,"height":768,"hidden":false,"anchorPoint":{"pointX":0.5,"pointY":0.5}},"layers":[{"animations":[],"initialState":{"affineTransform":[1,0,0,1,0,0],"masksToBounds":false,"rotation":0,"scale":1,"position":{"pointX":307.6939001083374,"pointY":44.95946034789085},"width":606.2812614440918,"sublayerTransform":[1,0,0,0,0,1,0,0,0,0,1,0,0,0,0,1],"contentsRect":{"y":0,"x":0,"width":1,"height":1},"opacity":1,"edgeAntialiasingMask":251658240,"height":92.49830907583237,"hidden":false,"anchorPoint":{"pointX":0.5,"pointY":0.5}},"objectID":"2CDC4591-DFBB-4DE9-AA07-4B4EDA5E9F98","layers":[{"animations":[],"layers":[],"initialState":{"affineTransform":[1,0,0,1,0,0],"masksToBounds":false,"rotation":0,"scale":1,"position":{"pointX":267.4467306137085,"pointY":53.28969419002533},"width":524,"sublayerTransform":[1,0,0,0,0,1,0,0,0,0,1,0,0,0,0,1],"contentsRect":{"y":0,"x":0,"width":1,"height":1},"opacity":1,"edgeAntialiasingMask":0,"height":70,"hidden":false,"anchorPoint":{"pointX":0.5,"pointY":0.5}},"texture":"26E1D36A86E033FA4AB154F481E23A88"}]}]},{"animations":[],"initialState":{"affineTransform":[1,0,0,1,0,0],"masksToBounds":false,"rotation":0,"scale":1,"position":{"pointX":512,"pointY":384},"width":1024,"sublayerTransform":[1,0,0,0,0,1,0,0,0,0,1,0,0,0,0,1],"contentsRect":{"y":0,"x":0,"width":1,"height":1},"opacity":1,"edgeAntialiasingMask":251658240,"height":768,"hidden":false,"anchorPoint":{"pointX":0.5,"pointY":0.5}},"layers":[{"animations":[],"initialState":{"affineTransform":[1,0,0,1,0,0],"masksToBounds":false,"rotation":0,"scale":1,"position":{"pointX":520.1402071490811,"pointY":103.0249404907227},"width":1037.232795193777,"sublayerTransform":[1,0,0,0,0,1,0,0,0,0,1,0,0,0,0,1],"contentsRect":{"y":0,"x":0,"width":1,"height":1},"opacity":1,"edgeAntialiasingMask":251658240,"height":1,"hidden":false,"anchorPoint":{"pointX":0.5,"pointY":0.5}},"objectID":"1BAAA411-4856-4BD7-8EA4-C0D0594F5DAA","layers":[{"animations":[],"layers":[],"initialState":{"affineTransform":[1,0,0,1,0,0],"masksToBounds":false,"rotation":0,"scale":1,"position":{"pointX":518.4761904478073,"pointY":0.4750595092773438},"width":1040,"sublayerTransform":[1,0,0,0,0,1,0,0,0,0,1,0,0,0,0,1],"contentsRect":{"y":0,"x":0,"width":1,"height":1},"opacity":1,"edgeAntialiasingMask":0,"height":4,"hidden":false,"anchorPoint":{"pointX":0.5,"pointY":0.5}},"texture":"15CA13132A771FE1DB043EB28E9335FD"}]}]},{"animations":[],"initialState":{"affineTransform":[1,0,0,1,0,0],"masksToBounds":false,"rotation":0,"scale":1,"position":{"pointX":512,"pointY":384},"width":1024,"sublayerTransform":[1,0,0,0,0,1,0,0,0,0,1,0,0,0,0,1],"contentsRect":{"y":0,"x":0,"width":1,"height":1},"opacity":1,"edgeAntialiasingMask":251658240,"height":768,"hidden":false,"anchorPoint":{"pointX":0.5,"pointY":0.5}},"layers":[{"animations":[],"initialState":{"affineTransform":[1,0,0,1,0,0],"masksToBounds":false,"rotation":0,"scale":1,"position":{"pointX":307.6938996315002,"pointY":138.3412780761719},"width":606.2812328338623,"sublayerTransform":[1,0,0,0,0,1,0,0,0,0,1,0,0,0,0,1],"contentsRect":{"y":0,"x":0,"width":1,"height":1},"opacity":1,"edgeAntialiasingMask":251658240,"height":55.0000011920929,"hidden":false,"anchorPoint":{"pointX":0.5,"pointY":0.5}},"objectID":"B7C6A886-DC3C-46F7-B6D2-9A96B7DDDAD8","layers":[{"animations":[],"layers":[],"initialState":{"affineTransform":[1,0,0,1,0,0],"masksToBounds":false,"rotation":0,"scale":1,"position":{"pointX":173.4467167854309,"pointY":25.15872251987457},"width":346,"sublayerTransform":[1,0,0,0,0,1,0,0,0,0,1,0,0,0,0,1],"contentsRect":{"y":0,"x":0,"width":1,"height":1},"opacity":1,"edgeAntialiasingMask":0,"height":32,"hidden":true,"anchorPoint":{"pointX":0.5,"pointY":0.5}},"texture":"D8446BA52186825C4BB28690774F6E66"}]}]},{"animations":[],"initialState":{"affineTransform":[1,0,0,1,0,0],"masksToBounds":false,"rotation":0,"scale":1,"position":{"pointX":512,"pointY":384},"width":1024,"sublayerTransform":[1,0,0,0,0,1,0,0,0,0,1,0,0,0,0,1],"contentsRect":{"y":0,"x":0,"width":1,"height":1},"opacity":1,"edgeAntialiasingMask":251658240,"height":768,"hidden":false,"anchorPoint":{"pointX":0.5,"pointY":0.5}},"layers":[{"animations":[],"initialState":{"affineTransform":[1,0,0,1,0,0],"masksToBounds":false,"rotation":0,"scale":1,"position":{"pointX":162.9237341880798,"pointY":247.1553344726562},"width":317.7279949188232,"sublayerTransform":[1,0,0,0,0,1,0,0,0,0,1,0,0,0,0,1],"contentsRect":{"y":0,"x":0,"width":1,"height":1},"opacity":1,"edgeAntialiasingMask":251658240,"height":36.00000143051147,"hidden":false,"anchorPoint":{"pointX":0.5,"pointY":0.5}},"objectID":"98DFA66F-2D6D-46D8-B947-206EE1C092C2","layers":[{"animations":[],"layers":[],"initialState":{"affineTransform":[1,0,0,1,0,0],"masksToBounds":false,"rotation":0,"scale":1,"position":{"pointX":158.9402632713318,"pointY":19.84466624259949},"width":314,"sublayerTransform":[1,0,0,0,0,1,0,0,0,0,1,0,0,0,0,1],"contentsRect":{"y":0,"x":0,"width":1,"height":1},"opacity":1,"edgeAntialiasingMask":0,"height":26,"hidden":true,"anchorPoint":{"pointX":0.5,"pointY":0.5}},"texture":"E3D145A6DF28781D6CA496FED15ABB33"}]}]},{"animations":[],"initialState":{"affineTransform":[1,0,0,1,0,0],"masksToBounds":false,"rotation":0,"scale":1,"position":{"pointX":512,"pointY":384},"width":1024,"sublayerTransform":[1,0,0,0,0,1,0,0,0,0,1,0,0,0,0,1],"contentsRect":{"y":0,"x":0,"width":1,"height":1},"opacity":1,"edgeAntialiasingMask":251658240,"height":768,"hidden":false,"anchorPoint":{"pointX":0.5,"pointY":0.5}},"layers":[{"animations":[],"initialState":{"affineTransform":[1,0,0,1,0,0],"masksToBounds":false,"rotation":0,"scale":1,"position":{"pointX":404.7680253982544,"pointY":508.4693908691406},"width":793.3680057525635,"sublayerTransform":[1,0,0,0,0,1,0,0,0,0,1,0,0,0,0,1],"contentsRect":{"y":0,"x":0,"width":1,"height":1},"opacity":1,"edgeAntialiasingMask":251658240,"height":251.9999980926514,"hidden":false,"anchorPoint":{"pointX":0.5,"pointY":0.5}},"objectID":"9B21E95E-28DA-49AC-92C3-8FDCB71B8691","layers":[{"animations":[],"layers":[],"initialState":{"affineTransform":[1,0,0,1,0,0],"masksToBounds":false,"rotation":0,"scale":1,"position":{"pointX":393.9159774780273,"pointY":126.0306081771851},"width":784,"sublayerTransform":[1,0,0,0,0,1,0,0,0,0,1,0,0,0,0,1],"contentsRect":{"y":0,"x":0,"width":1,"height":1},"opacity":1,"edgeAntialiasingMask":0,"height":241,"hidden":true,"anchorPoint":{"pointX":0.5,"pointY":0.5}},"texture":"9CA919AABBCA48D7E777A73FD1D23962"}]}]},{"animations":[],"initialState":{"affineTransform":[1,0,0,1,0,0],"masksToBounds":false,"rotation":0,"scale":1,"position":{"pointX":512,"pointY":384},"width":1024,"sublayerTransform":[1,0,0,0,0,1,0,0,0,0,1,0,0,0,0,1],"contentsRect":{"y":0,"x":0,"width":1,"height":1},"opacity":1,"edgeAntialiasingMask":251658240,"height":768,"hidden":false,"anchorPoint":{"pointX":0.5,"pointY":0.5}},"layers":[{"animations":[],"initialState":{"affineTransform":[1,0,0,1,0,0],"masksToBounds":false,"rotation":0,"scale":1,"position":{"pointX":57.88873434066772,"pointY":211.8390045166016},"width":105.3359985351562,"sublayerTransform":[1,0,0,0,0,1,0,0,0,0,1,0,0,0,0,1],"contentsRect":{"y":0,"x":0,"width":1,"height":1},"opacity":1,"edgeAntialiasingMask":251658240,"height":43.99999976158142,"hidden":false,"anchorPoint":{"pointX":0.5,"pointY":0.5}},"objectID":"070F2756-A875-4933-8ACB-CB38DB45EFA9","layers":[{"animations":[],"layers":[],"initialState":{"affineTransform":[1,0,0,1,0,0],"masksToBounds":false,"rotation":0,"scale":1,"position":{"pointX":53.2792649269104,"pointY":20.66099536418915},"width":99,"sublayerTransform":[1,0,0,0,0,1,0,0,0,0,1,0,0,0,0,1],"contentsRect":{"y":0,"x":0,"width":1,"height":1},"opacity":1,"edgeAntialiasingMask":0,"height":25,"hidden":true,"anchorPoint":{"pointX":0.5,"pointY":0.5}},"texture":"3D8F234DC2E9CD7213DBB953CE7F5F57"}]}]},{"animations":[],"initialState":{"affineTransform":[1,0,0,1,0,0],"masksToBounds":false,"rotation":0,"scale":1,"position":{"pointX":512,"pointY":384},"width":1024,"sublayerTransform":[1,0,0,0,0,1,0,0,0,0,1,0,0,0,0,1],"contentsRect":{"y":0,"x":0,"width":1,"height":1},"opacity":1,"edgeAntialiasingMask":251658240,"height":768,"hidden":false,"anchorPoint":{"pointX":0.5,"pointY":0.5}},"layers":[{"animations":[],"initialState":{"affineTransform":[1,0,0,1,0,0],"masksToBounds":false,"rotation":0,"scale":1,"position":{"pointX":90.29873609542847,"pointY":354.4693940458927},"width":170.1560020446777,"sublayerTransform":[1,0,0,0,0,1,0,0,0,0,1,0,0,0,0,1],"contentsRect":{"y":0,"x":0,"width":1,"height":1},"opacity":1,"edgeAntialiasingMask":251658240,"height":43.99999976158142,"hidden":false,"anchorPoint":{"pointX":0.5,"pointY":0.5}},"objectID":"BE2B5B47-ECB9-48A0-9B06-80506198F0F9","layers":[{"animations":[],"layers":[],"initialState":{"affineTransform":[1,0,0,1,0,0],"masksToBounds":false,"rotation":0,"scale":1,"position":{"pointX":84.7792649269104,"pointY":20.53060583489804},"width":162,"sublayerTransform":[1,0,0,0,0,1,0,0,0,0,1,0,0,0,0,1],"contentsRect":{"y":0,"x":0,"width":1,"height":1},"opacity":1,"edgeAntialiasingMask":0,"height":26,"hidden":true,"anchorPoint":{"pointX":0.5,"pointY":0.5}},"texture":"5EF0F4E6B479EFE482472867F30CA441"}]}]}]}},{"effects":[{"beginTime":0,"baseLayer":{"animations":[],"initialState":{"affineTransform":[1,0,0,1,0,0],"masksToBounds":false,"rotation":0,"scale":1,"position":{"pointX":57.88873434066772,"pointY":211.8390045166016},"width":105.3359985351562,"sublayerTransform":[1,0,0,0,0,1,0,0,0,0,1,0,0,0,0,1],"contentsRect":{"y":0,"x":0,"width":1,"height":1},"opacity":1,"edgeAntialiasingMask":251658240,"height":43.99999976158142,"hidden":false,"anchorPoint":{"pointX":0.5,"pointY":0.5}},"objectID":"070F2756-A875-4933-8ACB-CB38DB45EFA9","layers":[{"animations":[],"initialState":{"affineTransform":[1,0,0,1,0,0],"masksToBounds":false,"rotation":0,"scale":1,"position":{"pointX":506.7792649269104,"pointY":194.1609953641891},"width":105.3359985351562,"sublayerTransform":[1,0,0,0,0,1,0,0,0,0,1,-0.0004922987690640373,0,0,0,1],"contentsRect":{"y":0,"x":0,"width":1,"height":1},"opacity":1,"edgeAntialiasingMask":251658240,"height":43.99999976158142,"hidden":false,"anchorPoint":{"pointX":4.811073820672722,"pointY":4.412749918551607}},"layers":[{"animations":[{"timeOffset":0,"from":{"scalar":true},"beginTime":1e-100,"repeatCount":0,"fillMode":"both","property":"hidden","autoreverses":false,"duration":0.01,"to":{"scalar":false}}],"layers":[],"initialState":{"affineTransform":[1,0,0,1,0,0],"masksToBounds":false,"rotation":0,"scale":1,"position":{"pointX":53.2792649269104,"pointY":20.66099536418915},"width":99,"sublayerTransform":[1,0,0,0,0,1,0,0,0,0,1,0,0,0,0,1],"contentsRect":{"y":0,"x":0,"width":1,"height":1},"opacity":1,"edgeAntialiasingMask":0,"height":25,"hidden":true,"anchorPoint":{"pointX":0.5,"pointY":0.5}},"texture":"3D8F234DC2E9CD7213DBB953CE7F5F57"}]}]},"effects":[],"duration":0.01,"type":"buildIn","name":"apple:appear","objectID":"070F2756-A875-4933-8ACB-CB38DB45EFA9"},{"beginTime":0,"baseLayer":{"animations":[],"initialState":{"affineTransform":[1,0,0,1,0,0],"masksToBounds":false,"rotation":0,"scale":1,"position":{"pointX":162.9237341880798,"pointY":247.1553344726562},"width":317.7279949188232,"sublayerTransform":[1,0,0,0,0,1,0,0,0,0,1,0,0,0,0,1],"contentsRect":{"y":0,"x":0,"width":1,"height":1},"opacity":1,"edgeAntialiasingMask":251658240,"height":36.00000143051147,"hidden":false,"anchorPoint":{"pointX":0.5,"pointY":0.5}},"objectID":"98DFA66F-2D6D-46D8-B947-206EE1C092C2","layers":[{"animations":[],"initialState":{"affineTransform":[1,0,0,1,0,0],"masksToBounds":false,"rotation":0,"scale":1,"position":{"pointX":507.9402632713318,"pointY":154.8446662425995},"width":317.7279949188232,"sublayerTransform":[1,0,0,0,0,1,0,0,0,0,1,-0.0004922987690640373,0,0,0,1],"contentsRect":{"y":0,"x":0,"width":1,"height":1},"opacity":1,"edgeAntialiasingMask":251658240,"height":36.00000143051147,"hidden":false,"anchorPoint":{"pointX":1.598663861524403,"pointY":4.301240558045153}},"layers":[{"animations":[{"timeOffset":0,"from":{"scalar":true},"beginTime":1e-100,"repeatCount":0,"fillMode":"both","property":"hidden","autoreverses":false,"duration":0.01,"to":{"scalar":false}}],"layers":[],"initialState":{"affineTransform":[1,0,0,1,0,0],"masksToBounds":false,"rotation":0,"scale":1,"position":{"pointX":158.9402632713318,"pointY":19.84466624259949},"width":314,"sublayerTransform":[1,0,0,0,0,1,0,0,0,0,1,0,0,0,0,1],"contentsRect":{"y":0,"x":0,"width":1,"height":1},"opacity":1,"edgeAntialiasingMask":0,"height":26,"hidden":true,"anchorPoint":{"pointX":0.5,"pointY":0.5}},"texture":"E3D145A6DF28781D6CA496FED15ABB33"}]}]},"effects":[],"duration":0.01,"type":"buildIn","name":"apple:appear","objectID":"98DFA66F-2D6D-46D8-B947-206EE1C092C2"}],"automaticPlay":false,"hyperlinks":[],"accessibility":[{"text":"Avoid filters in views","targetRectangle":{"y":113.8412774801254,"x":7.553283214569092,"width":342.396,"height":49}},{"text":"ng-best-practices","targetRectangle":{"y":1.71030580997467,"x":7.553269386291504,"width":526.83125,"height":86}}],"baseLayer":{"animations":[],"initialState":{"affineTransform":[1,0,0,1,0,0],"masksToBounds":false,"rotation":0,"scale":1,"position":{"pointX":512,"pointY":384},"width":1024,"sublayerTransform":[1,0,0,0,0,1,0,0,0,0,1,0,0,0,0,1],"contentsRect":{"y":0,"x":0,"width":1,"height":1},"opacity":1,"edgeAntialiasingMask":251658240,"height":768,"hidden":false,"anchorPoint":{"pointX":0.5,"pointY":0.5}},"layers":[{"animations":[],"initialState":{"affineTransform":[1,0,0,1,0,0],"masksToBounds":false,"rotation":0,"scale":1,"position":{"pointX":512,"pointY":384},"width":1024,"sublayerTransform":[1,0,0,0,0,1,0,0,0,0,1,0,0,0,0,1],"contentsRect":{"y":0,"x":0,"width":1,"height":1},"opacity":1,"edgeAntialiasingMask":251658240,"height":768,"hidden":false,"anchorPoint":{"pointX":0.5,"pointY":0.5}},"layers":[{"animations":[],"initialState":{"affineTransform":[1,0,0,1,0,0],"masksToBounds":false,"rotation":0,"scale":1,"position":{"pointX":512,"pointY":384},"width":1024,"sublayerTransform":[1,0,0,0,0,1,0,0,0,0,1,0,0,0,0,1],"contentsRect":{"y":0,"x":0,"width":1,"height":1},"opacity":1,"edgeAntialiasingMask":251658240,"height":768,"hidden":false,"anchorPoint":{"pointX":0.5,"pointY":0.5}},"layers":[{"animations":[],"layers":[],"initialState":{"affineTransform":[1,0,0,1,0,0],"masksToBounds":false,"rotation":0,"scale":1,"position":{"pointX":512,"pointY":384},"width":1024,"sublayerTransform":[1,0,0,0,0,1,0,0,0,0,1,0,0,0,0,1],"contentsRect":{"y":0,"x":0,"width":1,"height":1},"opacity":1,"edgeAntialiasingMask":0,"height":768,"hidden":false,"anchorPoint":{"pointX":0.5,"pointY":0.5}},"texture":"FBB5DEA59905EE30EF2803B0A74DF992"}]}]},{"animations":[],"initialState":{"affineTransform":[1,0,0,1,0,0],"masksToBounds":false,"rotation":0,"scale":1,"position":{"pointX":512,"pointY":384},"width":1024,"sublayerTransform":[1,0,0,0,0,1,0,0,0,0,1,0,0,0,0,1],"contentsRect":{"y":0,"x":0,"width":1,"height":1},"opacity":1,"edgeAntialiasingMask":251658240,"height":768,"hidden":false,"anchorPoint":{"pointX":0.5,"pointY":0.5}},"layers":[{"animations":[],"initialState":{"affineTransform":[1,0,0,1,0,0],"masksToBounds":false,"rotation":0,"scale":1,"position":{"pointX":307.6939001083374,"pointY":44.95946034789085},"width":606.2812614440918,"sublayerTransform":[1,0,0,0,0,1,0,0,0,0,1,0,0,0,0,1],"contentsRect":{"y":0,"x":0,"width":1,"height":1},"opacity":1,"edgeAntialiasingMask":251658240,"height":92.49830907583237,"hidden":false,"anchorPoint":{"pointX":0.5,"pointY":0.5}},"objectID":"2CDC4591-DFBB-4DE9-AA07-4B4EDA5E9F98","layers":[{"animations":[],"layers":[],"initialState":{"affineTransform":[1,0,0,1,0,0],"masksToBounds":false,"rotation":0,"scale":1,"position":{"pointX":267.4467306137085,"pointY":53.28969419002533},"width":524,"sublayerTransform":[1,0,0,0,0,1,0,0,0,0,1,0,0,0,0,1],"contentsRect":{"y":0,"x":0,"width":1,"height":1},"opacity":1,"edgeAntialiasingMask":0,"height":70,"hidden":false,"anchorPoint":{"pointX":0.5,"pointY":0.5}},"texture":"26E1D36A86E033FA4AB154F481E23A88"}]}]},{"animations":[],"initialState":{"affineTransform":[1,0,0,1,0,0],"masksToBounds":false,"rotation":0,"scale":1,"position":{"pointX":512,"pointY":384},"width":1024,"sublayerTransform":[1,0,0,0,0,1,0,0,0,0,1,0,0,0,0,1],"contentsRect":{"y":0,"x":0,"width":1,"height":1},"opacity":1,"edgeAntialiasingMask":251658240,"height":768,"hidden":false,"anchorPoint":{"pointX":0.5,"pointY":0.5}},"layers":[{"animations":[],"initialState":{"affineTransform":[1,0,0,1,0,0],"masksToBounds":false,"rotation":0,"scale":1,"position":{"pointX":520.1402071490811,"pointY":103.0249404907227},"width":1037.232795193777,"sublayerTransform":[1,0,0,0,0,1,0,0,0,0,1,0,0,0,0,1],"contentsRect":{"y":0,"x":0,"width":1,"height":1},"opacity":1,"edgeAntialiasingMask":251658240,"height":1,"hidden":false,"anchorPoint":{"pointX":0.5,"pointY":0.5}},"objectID":"1BAAA411-4856-4BD7-8EA4-C0D0594F5DAA","layers":[{"animations":[],"layers":[],"initialState":{"affineTransform":[1,0,0,1,0,0],"masksToBounds":false,"rotation":0,"scale":1,"position":{"pointX":518.4761904478073,"pointY":0.4750595092773438},"width":1040,"sublayerTransform":[1,0,0,0,0,1,0,0,0,0,1,0,0,0,0,1],"contentsRect":{"y":0,"x":0,"width":1,"height":1},"opacity":1,"edgeAntialiasingMask":0,"height":4,"hidden":false,"anchorPoint":{"pointX":0.5,"pointY":0.5}},"texture":"15CA13132A771FE1DB043EB28E9335FD"}]}]},{"animations":[],"initialState":{"affineTransform":[1,0,0,1,0,0],"masksToBounds":false,"rotation":0,"scale":1,"position":{"pointX":512,"pointY":384},"width":1024,"sublayerTransform":[1,0,0,0,0,1,0,0,0,0,1,0,0,0,0,1],"contentsRect":{"y":0,"x":0,"width":1,"height":1},"opacity":1,"edgeAntialiasingMask":251658240,"height":768,"hidden":false,"anchorPoint":{"pointX":0.5,"pointY":0.5}},"layers":[{"animations":[],"initialState":{"affineTransform":[1,0,0,1,0,0],"masksToBounds":false,"rotation":0,"scale":1,"position":{"pointX":307.6938996315002,"pointY":138.3412780761719},"width":606.2812328338623,"sublayerTransform":[1,0,0,0,0,1,0,0,0,0,1,0,0,0,0,1],"contentsRect":{"y":0,"x":0,"width":1,"height":1},"opacity":1,"edgeAntialiasingMask":251658240,"height":55.0000011920929,"hidden":false,"anchorPoint":{"pointX":0.5,"pointY":0.5}},"objectID":"B7C6A886-DC3C-46F7-B6D2-9A96B7DDDAD8","layers":[{"animations":[],"layers":[],"initialState":{"affineTransform":[1,0,0,1,0,0],"masksToBounds":false,"rotation":0,"scale":1,"position":{"pointX":173.4467167854309,"pointY":25.15872251987457},"width":346,"sublayerTransform":[1,0,0,0,0,1,0,0,0,0,1,0,0,0,0,1],"contentsRect":{"y":0,"x":0,"width":1,"height":1},"opacity":1,"edgeAntialiasingMask":0,"height":32,"hidden":false,"anchorPoint":{"pointX":0.5,"pointY":0.5}},"texture":"D8446BA52186825C4BB28690774F6E66"}]}]},{"animations":[],"initialState":{"affineTransform":[1,0,0,1,0,0],"masksToBounds":false,"rotation":0,"scale":1,"position":{"pointX":512,"pointY":384},"width":1024,"sublayerTransform":[1,0,0,0,0,1,0,0,0,0,1,0,0,0,0,1],"contentsRect":{"y":0,"x":0,"width":1,"height":1},"opacity":1,"edgeAntialiasingMask":251658240,"height":768,"hidden":false,"anchorPoint":{"pointX":0.5,"pointY":0.5}},"layers":[{"animations":[],"initialState":{"affineTransform":[1,0,0,1,0,0],"masksToBounds":false,"rotation":0,"scale":1,"position":{"pointX":162.9237341880798,"pointY":247.1553344726562},"width":317.7279949188232,"sublayerTransform":[1,0,0,0,0,1,0,0,0,0,1,0,0,0,0,1],"contentsRect":{"y":0,"x":0,"width":1,"height":1},"opacity":1,"edgeAntialiasingMask":251658240,"height":36.00000143051147,"hidden":false,"anchorPoint":{"pointX":0.5,"pointY":0.5}},"objectID":"98DFA66F-2D6D-46D8-B947-206EE1C092C2","layers":[{"animations":[],"layers":[],"initialState":{"affineTransform":[1,0,0,1,0,0],"masksToBounds":false,"rotation":0,"scale":1,"position":{"pointX":158.9402632713318,"pointY":19.84466624259949},"width":314,"sublayerTransform":[1,0,0,0,0,1,0,0,0,0,1,0,0,0,0,1],"contentsRect":{"y":0,"x":0,"width":1,"height":1},"opacity":1,"edgeAntialiasingMask":0,"height":26,"hidden":true,"anchorPoint":{"pointX":0.5,"pointY":0.5}},"texture":"E3D145A6DF28781D6CA496FED15ABB33"}]}]},{"animations":[],"initialState":{"affineTransform":[1,0,0,1,0,0],"masksToBounds":false,"rotation":0,"scale":1,"position":{"pointX":512,"pointY":384},"width":1024,"sublayerTransform":[1,0,0,0,0,1,0,0,0,0,1,0,0,0,0,1],"contentsRect":{"y":0,"x":0,"width":1,"height":1},"opacity":1,"edgeAntialiasingMask":251658240,"height":768,"hidden":false,"anchorPoint":{"pointX":0.5,"pointY":0.5}},"layers":[{"animations":[],"initialState":{"affineTransform":[1,0,0,1,0,0],"masksToBounds":false,"rotation":0,"scale":1,"position":{"pointX":404.7680253982544,"pointY":508.4693908691406},"width":793.3680057525635,"sublayerTransform":[1,0,0,0,0,1,0,0,0,0,1,0,0,0,0,1],"contentsRect":{"y":0,"x":0,"width":1,"height":1},"opacity":1,"edgeAntialiasingMask":251658240,"height":251.9999980926514,"hidden":false,"anchorPoint":{"pointX":0.5,"pointY":0.5}},"objectID":"9B21E95E-28DA-49AC-92C3-8FDCB71B8691","layers":[{"animations":[],"layers":[],"initialState":{"affineTransform":[1,0,0,1,0,0],"masksToBounds":false,"rotation":0,"scale":1,"position":{"pointX":393.9159774780273,"pointY":126.0306081771851},"width":784,"sublayerTransform":[1,0,0,0,0,1,0,0,0,0,1,0,0,0,0,1],"contentsRect":{"y":0,"x":0,"width":1,"height":1},"opacity":1,"edgeAntialiasingMask":0,"height":241,"hidden":true,"anchorPoint":{"pointX":0.5,"pointY":0.5}},"texture":"9CA919AABBCA48D7E777A73FD1D23962"}]}]},{"animations":[],"initialState":{"affineTransform":[1,0,0,1,0,0],"masksToBounds":false,"rotation":0,"scale":1,"position":{"pointX":512,"pointY":384},"width":1024,"sublayerTransform":[1,0,0,0,0,1,0,0,0,0,1,0,0,0,0,1],"contentsRect":{"y":0,"x":0,"width":1,"height":1},"opacity":1,"edgeAntialiasingMask":251658240,"height":768,"hidden":false,"anchorPoint":{"pointX":0.5,"pointY":0.5}},"layers":[{"animations":[],"initialState":{"affineTransform":[1,0,0,1,0,0],"masksToBounds":false,"rotation":0,"scale":1,"position":{"pointX":57.88873434066772,"pointY":211.8390045166016},"width":105.3359985351562,"sublayerTransform":[1,0,0,0,0,1,0,0,0,0,1,0,0,0,0,1],"contentsRect":{"y":0,"x":0,"width":1,"height":1},"opacity":1,"edgeAntialiasingMask":251658240,"height":43.99999976158142,"hidden":false,"anchorPoint":{"pointX":0.5,"pointY":0.5}},"objectID":"070F2756-A875-4933-8ACB-CB38DB45EFA9","layers":[{"animations":[],"layers":[],"initialState":{"affineTransform":[1,0,0,1,0,0],"masksToBounds":false,"rotation":0,"scale":1,"position":{"pointX":53.2792649269104,"pointY":20.66099536418915},"width":99,"sublayerTransform":[1,0,0,0,0,1,0,0,0,0,1,0,0,0,0,1],"contentsRect":{"y":0,"x":0,"width":1,"height":1},"opacity":1,"edgeAntialiasingMask":0,"height":25,"hidden":true,"anchorPoint":{"pointX":0.5,"pointY":0.5}},"texture":"3D8F234DC2E9CD7213DBB953CE7F5F57"}]}]},{"animations":[],"initialState":{"affineTransform":[1,0,0,1,0,0],"masksToBounds":false,"rotation":0,"scale":1,"position":{"pointX":512,"pointY":384},"width":1024,"sublayerTransform":[1,0,0,0,0,1,0,0,0,0,1,0,0,0,0,1],"contentsRect":{"y":0,"x":0,"width":1,"height":1},"opacity":1,"edgeAntialiasingMask":251658240,"height":768,"hidden":false,"anchorPoint":{"pointX":0.5,"pointY":0.5}},"layers":[{"animations":[],"initialState":{"affineTransform":[1,0,0,1,0,0],"masksToBounds":false,"rotation":0,"scale":1,"position":{"pointX":90.29873609542847,"pointY":354.4693940458927},"width":170.1560020446777,"sublayerTransform":[1,0,0,0,0,1,0,0,0,0,1,0,0,0,0,1],"contentsRect":{"y":0,"x":0,"width":1,"height":1},"opacity":1,"edgeAntialiasingMask":251658240,"height":43.99999976158142,"hidden":false,"anchorPoint":{"pointX":0.5,"pointY":0.5}},"objectID":"BE2B5B47-ECB9-48A0-9B06-80506198F0F9","layers":[{"animations":[],"layers":[],"initialState":{"affineTransform":[1,0,0,1,0,0],"masksToBounds":false,"rotation":0,"scale":1,"position":{"pointX":84.7792649269104,"pointY":20.53060583489804},"width":162,"sublayerTransform":[1,0,0,0,0,1,0,0,0,0,1,0,0,0,0,1],"contentsRect":{"y":0,"x":0,"width":1,"height":1},"opacity":1,"edgeAntialiasingMask":0,"height":26,"hidden":true,"anchorPoint":{"pointX":0.5,"pointY":0.5}},"texture":"5EF0F4E6B479EFE482472867F30CA441"}]}]}]}},{"effects":[{"beginTime":0,"baseLayer":{"animations":[],"initialState":{"affineTransform":[1,0,0,1,0,0],"masksToBounds":false,"rotation":0,"scale":1,"position":{"pointX":90.29873609542847,"pointY":354.4693940458927},"width":170.1560020446777,"sublayerTransform":[1,0,0,0,0,1,0,0,0,0,1,0,0,0,0,1],"contentsRect":{"y":0,"x":0,"width":1,"height":1},"opacity":1,"edgeAntialiasingMask":251658240,"height":43.99999976158142,"hidden":false,"anchorPoint":{"pointX":0.5,"pointY":0.5}},"objectID":"BE2B5B47-ECB9-48A0-9B06-80506198F0F9","layers":[{"animations":[],"initialState":{"affineTransform":[1,0,0,1,0,0],"masksToBounds":false,"rotation":0,"scale":1,"position":{"pointX":506.7792649269104,"pointY":51.53060583489804},"width":170.1560020446777,"sublayerTransform":[1,0,0,0,0,1,0,0,0,0,1,-0.0004922987690640373,0,0,0,1],"contentsRect":{"y":0,"x":0,"width":1,"height":1},"opacity":1,"edgeAntialiasingMask":251658240,"height":43.99999976158142,"hidden":false,"anchorPoint":{"pointX":2.978321415860757,"pointY":1.171150138957318}},"layers":[{"animations":[{"timeOffset":0,"from":{"scalar":true},"beginTime":1e-100,"repeatCount":0,"fillMode":"both","property":"hidden","autoreverses":false,"duration":0.01,"to":{"scalar":false}}],"layers":[],"initialState":{"affineTransform":[1,0,0,1,0,0],"masksToBounds":false,"rotation":0,"scale":1,"position":{"pointX":84.7792649269104,"pointY":20.53060583489804},"width":162,"sublayerTransform":[1,0,0,0,0,1,0,0,0,0,1,0,0,0,0,1],"contentsRect":{"y":0,"x":0,"width":1,"height":1},"opacity":1,"edgeAntialiasingMask":0,"height":26,"hidden":true,"anchorPoint":{"pointX":0.5,"pointY":0.5}},"texture":"5EF0F4E6B479EFE482472867F30CA441"}]}]},"effects":[],"duration":0.01,"type":"buildIn","name":"apple:appear","objectID":"BE2B5B47-ECB9-48A0-9B06-80506198F0F9"},{"beginTime":0,"baseLayer":{"animations":[],"initialState":{"affineTransform":[1,0,0,1,0,0],"masksToBounds":false,"rotation":0,"scale":1,"position":{"pointX":404.7680253982544,"pointY":508.4693908691406},"width":793.3680057525635,"sublayerTransform":[1,0,0,0,0,1,0,0,0,0,1,0,0,0,0,1],"contentsRect":{"y":0,"x":0,"width":1,"height":1},"opacity":1,"edgeAntialiasingMask":251658240,"height":251.9999980926514,"hidden":false,"anchorPoint":{"pointX":0.5,"pointY":0.5}},"objectID":"9B21E95E-28DA-49AC-92C3-8FDCB71B8691","layers":[{"animations":[],"initialState":{"affineTransform":[1,0,0,1,0,0],"masksToBounds":false,"rotation":0,"scale":1,"position":{"pointX":503.9159774780273,"pointY":1.530608177185059},"width":793.3680057525635,"sublayerTransform":[1,0,0,0,0,1,0,0,0,0,1,-0.0004922987690640373,0,0,0,1],"contentsRect":{"y":0,"x":0,"width":1,"height":1},"opacity":1,"edgeAntialiasingMask":251658240,"height":251.9999980926514,"hidden":false,"anchorPoint":{"pointX":0.6351604473891391,"pointY":0.006073842018928543}},"layers":[{"animations":[{"timeOffset":0,"from":{"scalar":true},"beginTime":1e-100,"repeatCount":0,"fillMode":"both","property":"hidden","autoreverses":false,"duration":0.01,"to":{"scalar":false}}],"layers":[],"initialState":{"affineTransform":[1,0,0,1,0,0],"masksToBounds":false,"rotation":0,"scale":1,"position":{"pointX":393.9159774780273,"pointY":126.0306081771851},"width":784,"sublayerTransform":[1,0,0,0,0,1,0,0,0,0,1,0,0,0,0,1],"contentsRect":{"y":0,"x":0,"width":1,"height":1},"opacity":1,"edgeAntialiasingMask":0,"height":241,"hidden":true,"anchorPoint":{"pointX":0.5,"pointY":0.5}},"texture":"9CA919AABBCA48D7E777A73FD1D23962"}]}]},"effects":[],"duration":0.01,"type":"buildIn","name":"apple:appear","objectID":"9B21E95E-28DA-49AC-92C3-8FDCB71B8691"}],"automaticPlay":false,"hyperlinks":[],"accessibility":[{"text":"Avoid filters in views","targetRectangle":{"y":113.8412774801254,"x":7.553283214569092,"width":342.396,"height":49}},{"text":"{{someModel.name | titlecase}}","targetRectangle":{"y":232.1553337574005,"x":7.059736728668213,"width":310.728,"height":30}},{"text":"In view:","targetRectangle":{"y":192.8390046358109,"x":8.2207350730896,"width":98.33600000000001,"height":38}},{"text":"ng-best-practices","targetRectangle":{"y":1.71030580997467,"x":7.553269386291504,"width":526.83125,"height":86}}],"baseLayer":{"animations":[],"initialState":{"affineTransform":[1,0,0,1,0,0],"masksToBounds":false,"rotation":0,"scale":1,"position":{"pointX":512,"pointY":384},"width":1024,"sublayerTransform":[1,0,0,0,0,1,0,0,0,0,1,0,0,0,0,1],"contentsRect":{"y":0,"x":0,"width":1,"height":1},"opacity":1,"edgeAntialiasingMask":251658240,"height":768,"hidden":false,"anchorPoint":{"pointX":0.5,"pointY":0.5}},"layers":[{"animations":[],"initialState":{"affineTransform":[1,0,0,1,0,0],"masksToBounds":false,"rotation":0,"scale":1,"position":{"pointX":512,"pointY":384},"width":1024,"sublayerTransform":[1,0,0,0,0,1,0,0,0,0,1,0,0,0,0,1],"contentsRect":{"y":0,"x":0,"width":1,"height":1},"opacity":1,"edgeAntialiasingMask":251658240,"height":768,"hidden":false,"anchorPoint":{"pointX":0.5,"pointY":0.5}},"layers":[{"animations":[],"initialState":{"affineTransform":[1,0,0,1,0,0],"masksToBounds":false,"rotation":0,"scale":1,"position":{"pointX":512,"pointY":384},"width":1024,"sublayerTransform":[1,0,0,0,0,1,0,0,0,0,1,0,0,0,0,1],"contentsRect":{"y":0,"x":0,"width":1,"height":1},"opacity":1,"edgeAntialiasingMask":251658240,"height":768,"hidden":false,"anchorPoint":{"pointX":0.5,"pointY":0.5}},"layers":[{"animations":[],"layers":[],"initialState":{"affineTransform":[1,0,0,1,0,0],"masksToBounds":false,"rotation":0,"scale":1,"position":{"pointX":512,"pointY":384},"width":1024,"sublayerTransform":[1,0,0,0,0,1,0,0,0,0,1,0,0,0,0,1],"contentsRect":{"y":0,"x":0,"width":1,"height":1},"opacity":1,"edgeAntialiasingMask":0,"height":768,"hidden":false,"anchorPoint":{"pointX":0.5,"pointY":0.5}},"texture":"FBB5DEA59905EE30EF2803B0A74DF992"}]}]},{"animations":[],"initialState":{"affineTransform":[1,0,0,1,0,0],"masksToBounds":false,"rotation":0,"scale":1,"position":{"pointX":512,"pointY":384},"width":1024,"sublayerTransform":[1,0,0,0,0,1,0,0,0,0,1,0,0,0,0,1],"contentsRect":{"y":0,"x":0,"width":1,"height":1},"opacity":1,"edgeAntialiasingMask":251658240,"height":768,"hidden":false,"anchorPoint":{"pointX":0.5,"pointY":0.5}},"layers":[{"animations":[],"initialState":{"affineTransform":[1,0,0,1,0,0],"masksToBounds":false,"rotation":0,"scale":1,"position":{"pointX":307.6939001083374,"pointY":44.95946034789085},"width":606.2812614440918,"sublayerTransform":[1,0,0,0,0,1,0,0,0,0,1,0,0,0,0,1],"contentsRect":{"y":0,"x":0,"width":1,"height":1},"opacity":1,"edgeAntialiasingMask":251658240,"height":92.49830907583237,"hidden":false,"anchorPoint":{"pointX":0.5,"pointY":0.5}},"objectID":"2CDC4591-DFBB-4DE9-AA07-4B4EDA5E9F98","layers":[{"animations":[],"layers":[],"initialState":{"affineTransform":[1,0,0,1,0,0],"masksToBounds":false,"rotation":0,"scale":1,"position":{"pointX":267.4467306137085,"pointY":53.28969419002533},"width":524,"sublayerTransform":[1,0,0,0,0,1,0,0,0,0,1,0,0,0,0,1],"contentsRect":{"y":0,"x":0,"width":1,"height":1},"opacity":1,"edgeAntialiasingMask":0,"height":70,"hidden":false,"anchorPoint":{"pointX":0.5,"pointY":0.5}},"texture":"26E1D36A86E033FA4AB154F481E23A88"}]}]},{"animations":[],"initialState":{"affineTransform":[1,0,0,1,0,0],"masksToBounds":false,"rotation":0,"scale":1,"position":{"pointX":512,"pointY":384},"width":1024,"sublayerTransform":[1,0,0,0,0,1,0,0,0,0,1,0,0,0,0,1],"contentsRect":{"y":0,"x":0,"width":1,"height":1},"opacity":1,"edgeAntialiasingMask":251658240,"height":768,"hidden":false,"anchorPoint":{"pointX":0.5,"pointY":0.5}},"layers":[{"animations":[],"initialState":{"affineTransform":[1,0,0,1,0,0],"masksToBounds":false,"rotation":0,"scale":1,"position":{"pointX":520.1402071490811,"pointY":103.0249404907227},"width":1037.232795193777,"sublayerTransform":[1,0,0,0,0,1,0,0,0,0,1,0,0,0,0,1],"contentsRect":{"y":0,"x":0,"width":1,"height":1},"opacity":1,"edgeAntialiasingMask":251658240,"height":1,"hidden":false,"anchorPoint":{"pointX":0.5,"pointY":0.5}},"objectID":"1BAAA411-4856-4BD7-8EA4-C0D0594F5DAA","layers":[{"animations":[],"layers":[],"initialState":{"affineTransform":[1,0,0,1,0,0],"masksToBounds":false,"rotation":0,"scale":1,"position":{"pointX":518.4761904478073,"pointY":0.4750595092773438},"width":1040,"sublayerTransform":[1,0,0,0,0,1,0,0,0,0,1,0,0,0,0,1],"contentsRect":{"y":0,"x":0,"width":1,"height":1},"opacity":1,"edgeAntialiasingMask":0,"height":4,"hidden":false,"anchorPoint":{"pointX":0.5,"pointY":0.5}},"texture":"15CA13132A771FE1DB043EB28E9335FD"}]}]},{"animations":[],"initialState":{"affineTransform":[1,0,0,1,0,0],"masksToBounds":false,"rotation":0,"scale":1,"position":{"pointX":512,"pointY":384},"width":1024,"sublayerTransform":[1,0,0,0,0,1,0,0,0,0,1,0,0,0,0,1],"contentsRect":{"y":0,"x":0,"width":1,"height":1},"opacity":1,"edgeAntialiasingMask":251658240,"height":768,"hidden":false,"anchorPoint":{"pointX":0.5,"pointY":0.5}},"layers":[{"animations":[],"initialState":{"affineTransform":[1,0,0,1,0,0],"masksToBounds":false,"rotation":0,"scale":1,"position":{"pointX":307.6938996315002,"pointY":138.3412780761719},"width":606.2812328338623,"sublayerTransform":[1,0,0,0,0,1,0,0,0,0,1,0,0,0,0,1],"contentsRect":{"y":0,"x":0,"width":1,"height":1},"opacity":1,"edgeAntialiasingMask":251658240,"height":55.0000011920929,"hidden":false,"anchorPoint":{"pointX":0.5,"pointY":0.5}},"objectID":"B7C6A886-DC3C-46F7-B6D2-9A96B7DDDAD8","layers":[{"animations":[],"layers":[],"initialState":{"affineTransform":[1,0,0,1,0,0],"masksToBounds":false,"rotation":0,"scale":1,"position":{"pointX":173.4467167854309,"pointY":25.15872251987457},"width":346,"sublayerTransform":[1,0,0,0,0,1,0,0,0,0,1,0,0,0,0,1],"contentsRect":{"y":0,"x":0,"width":1,"height":1},"opacity":1,"edgeAntialiasingMask":0,"height":32,"hidden":false,"anchorPoint":{"pointX":0.5,"pointY":0.5}},"texture":"D8446BA52186825C4BB28690774F6E66"}]}]},{"animations":[],"initialState":{"affineTransform":[1,0,0,1,0,0],"masksToBounds":false,"rotation":0,"scale":1,"position":{"pointX":512,"pointY":384},"width":1024,"sublayerTransform":[1,0,0,0,0,1,0,0,0,0,1,0,0,0,0,1],"contentsRect":{"y":0,"x":0,"width":1,"height":1},"opacity":1,"edgeAntialiasingMask":251658240,"height":768,"hidden":false,"anchorPoint":{"pointX":0.5,"pointY":0.5}},"layers":[{"animations":[],"initialState":{"affineTransform":[1,0,0,1,0,0],"masksToBounds":false,"rotation":0,"scale":1,"position":{"pointX":162.9237341880798,"pointY":247.1553344726562},"width":317.7279949188232,"sublayerTransform":[1,0,0,0,0,1,0,0,0,0,1,0,0,0,0,1],"contentsRect":{"y":0,"x":0,"width":1,"height":1},"opacity":1,"edgeAntialiasingMask":251658240,"height":36.00000143051147,"hidden":false,"anchorPoint":{"pointX":0.5,"pointY":0.5}},"objectID":"98DFA66F-2D6D-46D8-B947-206EE1C092C2","layers":[{"animations":[],"layers":[],"initialState":{"affineTransform":[1,0,0,1,0,0],"masksToBounds":false,"rotation":0,"scale":1,"position":{"pointX":158.9402632713318,"pointY":19.84466624259949},"width":314,"sublayerTransform":[1,0,0,0,0,1,0,0,0,0,1,0,0,0,0,1],"contentsRect":{"y":0,"x":0,"width":1,"height":1},"opacity":1,"edgeAntialiasingMask":0,"height":26,"hidden":false,"anchorPoint":{"pointX":0.5,"pointY":0.5}},"texture":"E3D145A6DF28781D6CA496FED15ABB33"}]}]},{"animations":[],"initialState":{"affineTransform":[1,0,0,1,0,0],"masksToBounds":false,"rotation":0,"scale":1,"position":{"pointX":512,"pointY":384},"width":1024,"sublayerTransform":[1,0,0,0,0,1,0,0,0,0,1,0,0,0,0,1],"contentsRect":{"y":0,"x":0,"width":1,"height":1},"opacity":1,"edgeAntialiasingMask":251658240,"height":768,"hidden":false,"anchorPoint":{"pointX":0.5,"pointY":0.5}},"layers":[{"animations":[],"initialState":{"affineTransform":[1,0,0,1,0,0],"masksToBounds":false,"rotation":0,"scale":1,"position":{"pointX":404.7680253982544,"pointY":508.4693908691406},"width":793.3680057525635,"sublayerTransform":[1,0,0,0,0,1,0,0,0,0,1,0,0,0,0,1],"contentsRect":{"y":0,"x":0,"width":1,"height":1},"opacity":1,"edgeAntialiasingMask":251658240,"height":251.9999980926514,"hidden":false,"anchorPoint":{"pointX":0.5,"pointY":0.5}},"objectID":"9B21E95E-28DA-49AC-92C3-8FDCB71B8691","layers":[{"animations":[],"layers":[],"initialState":{"affineTransform":[1,0,0,1,0,0],"masksToBounds":false,"rotation":0,"scale":1,"position":{"pointX":393.9159774780273,"pointY":126.0306081771851},"width":784,"sublayerTransform":[1,0,0,0,0,1,0,0,0,0,1,0,0,0,0,1],"contentsRect":{"y":0,"x":0,"width":1,"height":1},"opacity":1,"edgeAntialiasingMask":0,"height":241,"hidden":true,"anchorPoint":{"pointX":0.5,"pointY":0.5}},"texture":"9CA919AABBCA48D7E777A73FD1D23962"}]}]},{"animations":[],"initialState":{"affineTransform":[1,0,0,1,0,0],"masksToBounds":false,"rotation":0,"scale":1,"position":{"pointX":512,"pointY":384},"width":1024,"sublayerTransform":[1,0,0,0,0,1,0,0,0,0,1,0,0,0,0,1],"contentsRect":{"y":0,"x":0,"width":1,"height":1},"opacity":1,"edgeAntialiasingMask":251658240,"height":768,"hidden":false,"anchorPoint":{"pointX":0.5,"pointY":0.5}},"layers":[{"animations":[],"initialState":{"affineTransform":[1,0,0,1,0,0],"masksToBounds":false,"rotation":0,"scale":1,"position":{"pointX":57.88873434066772,"pointY":211.8390045166016},"width":105.3359985351562,"sublayerTransform":[1,0,0,0,0,1,0,0,0,0,1,0,0,0,0,1],"contentsRect":{"y":0,"x":0,"width":1,"height":1},"opacity":1,"edgeAntialiasingMask":251658240,"height":43.99999976158142,"hidden":false,"anchorPoint":{"pointX":0.5,"pointY":0.5}},"objectID":"070F2756-A875-4933-8ACB-CB38DB45EFA9","layers":[{"animations":[],"layers":[],"initialState":{"affineTransform":[1,0,0,1,0,0],"masksToBounds":false,"rotation":0,"scale":1,"position":{"pointX":53.2792649269104,"pointY":20.66099536418915},"width":99,"sublayerTransform":[1,0,0,0,0,1,0,0,0,0,1,0,0,0,0,1],"contentsRect":{"y":0,"x":0,"width":1,"height":1},"opacity":1,"edgeAntialiasingMask":0,"height":25,"hidden":false,"anchorPoint":{"pointX":0.5,"pointY":0.5}},"texture":"3D8F234DC2E9CD7213DBB953CE7F5F57"}]}]},{"animations":[],"initialState":{"affineTransform":[1,0,0,1,0,0],"masksToBounds":false,"rotation":0,"scale":1,"position":{"pointX":512,"pointY":384},"width":1024,"sublayerTransform":[1,0,0,0,0,1,0,0,0,0,1,0,0,0,0,1],"contentsRect":{"y":0,"x":0,"width":1,"height":1},"opacity":1,"edgeAntialiasingMask":251658240,"height":768,"hidden":false,"anchorPoint":{"pointX":0.5,"pointY":0.5}},"layers":[{"animations":[],"initialState":{"affineTransform":[1,0,0,1,0,0],"masksToBounds":false,"rotation":0,"scale":1,"position":{"pointX":90.29873609542847,"pointY":354.4693940458927},"width":170.1560020446777,"sublayerTransform":[1,0,0,0,0,1,0,0,0,0,1,0,0,0,0,1],"contentsRect":{"y":0,"x":0,"width":1,"height":1},"opacity":1,"edgeAntialiasingMask":251658240,"height":43.99999976158142,"hidden":false,"anchorPoint":{"pointX":0.5,"pointY":0.5}},"objectID":"BE2B5B47-ECB9-48A0-9B06-80506198F0F9","layers":[{"animations":[],"layers":[],"initialState":{"affineTransform":[1,0,0,1,0,0],"masksToBounds":false,"rotation":0,"scale":1,"position":{"pointX":84.7792649269104,"pointY":20.53060583489804},"width":162,"sublayerTransform":[1,0,0,0,0,1,0,0,0,0,1,0,0,0,0,1],"contentsRect":{"y":0,"x":0,"width":1,"height":1},"opacity":1,"edgeAntialiasingMask":0,"height":26,"hidden":true,"anchorPoint":{"pointX":0.5,"pointY":0.5}},"texture":"5EF0F4E6B479EFE482472867F30CA441"}]}]}]}},{"effects":[{"beginTime":0,"baseLayer":{"animations":[],"initialState":{"affineTransform":[1,0,0,1,0,0],"masksToBounds":false,"rotation":0,"scale":1,"position":{"pointX":512,"pointY":384},"width":1024,"sublayerTransform":[1,0,0,0,0,1,0,0,0,0,1,0,0,0,0,1],"contentsRect":{"y":0,"x":0,"width":1,"height":1},"opacity":1,"edgeAntialiasingMask":251658240,"height":768,"hidden":false,"anchorPoint":{"pointX":0.5,"pointY":0.5}},"objectID":"0","layers":[{"animations":[],"initialState":{"affineTransform":[1,0,0,1,0,0],"masksToBounds":false,"rotation":0,"scale":1,"position":{"pointX":512,"pointY":384},"width":1024,"sublayerTransform":[1,0,0,0,0,1,0,0,0,0,1,-0.0004922987690640373,0,0,0,1],"contentsRect":{"y":0,"x":0,"width":1,"height":1},"opacity":1,"edgeAntialiasingMask":251658240,"height":768,"hidden":false,"anchorPoint":{"pointX":0.5,"pointY":0.5}},"layers":[{"animations":[],"layers":[],"initialState":{"affineTransform":[1,0,0,1,0,0],"masksToBounds":false,"rotation":0,"scale":1,"position":{"pointX":512,"pointY":384},"width":1024,"sublayerTransform":[1,0,0,0,0,1,0,0,0,0,1,0,0,0,0,1],"contentsRect":{"y":0,"x":0,"width":1,"height":1},"opacity":1,"edgeAntialiasingMask":0,"height":768,"hidden":false,"anchorPoint":{"pointX":0.5,"pointY":0.5}},"texture":"A8CE3FB2D25C34E000D23C6DCD563D2B"},{"animations":[{"timeOffset":0,"from":{"scalar":false},"beginTime":0,"repeatCount":0,"fillMode":"both","property":"hidden","autoreverses":false,"duration":0.01,"to":{"scalar":true}}],"layers":[],"initialState":{"affineTransform":[1,0,0,1,0,0],"masksToBounds":false,"rotation":0,"scale":1,"position":{"pointX":512,"pointY":384},"width":1024,"sublayerTransform":[1,0,0,0,0,1,0,0,0,0,1,0,0,0,0,1],"contentsRect":{"y":0,"x":0,"width":1,"height":1},"opacity":1,"edgeAntialiasingMask":0,"height":768,"hidden":false,"anchorPoint":{"pointX":0.5,"pointY":0.5}},"texture":"15B89F6380020007C90634177F53413D"}]}]},"effects":[],"duration":0.01,"type":"transition","name":"none","objectID":"0"}],"automaticPlay":false,"hyperlinks":[],"accessibility":[{"text":"Avoid filters in views","targetRectangle":{"y":113.8412774801254,"x":7.553283214569092,"width":342.396,"height":49}},{"text":"{{someModel.name | titlecase}}","targetRectangle":{"y":232.1553337574005,"x":7.059736728668213,"width":310.728,"height":30}},{"text":"In view:","targetRectangle":{"y":192.8390046358109,"x":8.2207350730896,"width":98.33600000000001,"height":38}},{"text":"In controller:","targetRectangle":{"y":335.469394165102,"x":8.2207350730896,"width":163.156,"height":38}},{"text":"angular.module('myApp').controller('MyCtrl', function ($scope, $http, $filter) {","targetRectangle":{"y":385.4693918228149,"x":11.08402252197266,"width":780.8680000000001,"height":36}},{"text":"$http.get('/someModel')","targetRectangle":{"y":421.4693918228149,"x":11.08402252197266,"width":247.874,"height":36}},{"text":"    .success(function (data) {","targetRectangle":{"y":457.4693918228149,"x":11.08402252197266,"width":270.182,"height":36}},{"text":"      $scope.someModel = data;","targetRectangle":{"y":493.4693918228149,"x":11.08402252197266,"width":310.398,"height":36}},{"text":"      $scope.someModel.name = $filter('titlecase')($scope.someModel.name);","targetRectangle":{"y":529.4693918228149,"x":11.08402252197266,"width":773.1679999999999,"height":36}},{"text":"    });","targetRectangle":{"y":565.4693918228149,"x":11.08402252197266,"width":42.46,"height":36}},{"text":"});","targetRectangle":{"y":601.4693918228149,"x":11.08402252197266,"width":20.46,"height":30}},{"text":"ng-best-practices","targetRectangle":{"y":1.71030580997467,"x":7.553269386291504,"width":526.83125,"height":86}}],"baseLayer":{"animations":[],"initialState":{"affineTransform":[1,0,0,1,0,0],"masksToBounds":false,"rotation":0,"scale":1,"position":{"pointX":512,"pointY":384},"width":1024,"sublayerTransform":[1,0,0,0,0,1,0,0,0,0,1,0,0,0,0,1],"contentsRect":{"y":0,"x":0,"width":1,"height":1},"opacity":1,"edgeAntialiasingMask":251658240,"height":768,"hidden":false,"anchorPoint":{"pointX":0.5,"pointY":0.5}},"objectID":"0","layers":[{"animations":[],"initialState":{"affineTransform":[1,0,0,1,0,0],"masksToBounds":false,"rotation":0,"scale":1,"position":{"pointX":512,"pointY":384},"width":1024,"sublayerTransform":[1,0,0,0,0,1,0,0,0,0,1,-0.0004922987690640373,0,0,0,1],"contentsRect":{"y":0,"x":0,"width":1,"height":1},"opacity":1,"edgeAntialiasingMask":251658240,"height":768,"hidden":false,"anchorPoint":{"pointX":0.5,"pointY":0.5}},"layers":[{"animations":[],"layers":[],"initialState":{"affineTransform":[1,0,0,1,0,0],"masksToBounds":false,"rotation":0,"scale":1,"position":{"pointX":512,"pointY":384},"width":1024,"sublayerTransform":[1,0,0,0,0,1,0,0,0,0,1,0,0,0,0,1],"contentsRect":{"y":0,"x":0,"width":1,"height":1},"opacity":1,"edgeAntialiasingMask":0,"height":768,"hidden":false,"anchorPoint":{"pointX":0.5,"pointY":0.5}},"texture":"15B89F6380020007C90634177F53413D"}]}]}}]}