{"assets":{"FBB5DEA59905EE30EF2803B0A74DF992":{"type":"texture","index":85,"assetRequest":{"type":"slide","state":"contents","slide":"6E5F5B76-4585-4DB2-993F-0697D421B839"},"url":{"web":"assets/FBB5DEA59905EE30EF2803B0A74DF992.svg"},"width":1024,"height":768},"B3B9AA996F79885C6FAB5E6D0A29C9E9":{"type":"texture","index":92,"assetRequest":{"type":"slide","state":"outgoing","slide":"6E5F5B76-4585-4DB2-993F-0697D421B839"},"url":{"web":"assets/B3B9AA996F79885C6FAB5E6D0A29C9E9.svg"},"width":1024,"height":768},"A7B691CCA327CFDA5B5EAB08D630A73B":{"type":"texture","index":88,"assetRequest":{"type":"slide","state":"contents","slide":"6E5F5B76-4585-4DB2-993F-0697D421B839"},"url":{"web":"assets/A7B691CCA327CFDA5B5EAB08D630A73B.svg"},"width":348,"height":40},"5DC4798C72AE6D64ACFE95104A79F431":{"type":"texture","index":90,"assetRequest":{"type":"slide","state":"contents","slide":"6E5F5B76-4585-4DB2-993F-0697D421B839"},"url":{"web":"assets/5DC4798C72AE6D64ACFE95104A79F431.svg"},"width":265,"height":174},"15CA13132A771FE1DB043EB28E9335FD":{"type":"texture","index":87,"assetRequest":{"type":"slide","state":"contents","slide":"6E5F5B76-4585-4DB2-993F-0697D421B839"},"url":{"web":"assets/15CA13132A771FE1DB043EB28E9335FD.svg"},"width":1040,"height":4},"BFB39CA5157C9F5512005187072B4883":{"type":"texture","index":89,"assetRequest":{"type":"slide","state":"contents","slide":"6E5F5B76-4585-4DB2-993F-0697D421B839"},"url":{"web":"assets/BFB39CA5157C9F5512005187072B4883.svg"},"width":265,"height":577},"C31DA9B4D76CAB45EBF603B063E74579":{"type":"texture","index":93,"assetRequest":{"type":"slide","state":"incoming","slide":"FFE1343B-5207-4972-8353-5646303D588C"},"url":{"web":"assets/C31DA9B4D76CAB45EBF603B063E74579.svg"},"width":1024,"height":768},"27A4F9539C29228641EB2997E798939E":{"type":"texture","index":91,"assetRequest":{"type":"slide","state":"contents","slide":"6E5F5B76-4585-4DB2-993F-0697D421B839"},"url":{"web":"assets/27A4F9539C29228641EB2997E798939E.svg"},"width":483,"height":56},"26E1D36A86E033FA4AB154F481E23A88":{"type":"texture","index":86,"assetRequest":{"type":"slide","state":"contents","slide":"6E5F5B76-4585-4DB2-993F-0697D421B839"},"url":{"web":"assets/26E1D36A86E033FA4AB154F481E23A88.svg"},"width":524,"height":70}},"events":[{"effects":[{"beginTime":0,"baseLayer":{"animations":[],"initialState":{"affineTransform":[1,0,0,1,0,0],"masksToBounds":false,"rotation":0,"scale":1,"position":{"pointX":307.6938996315002,"pointY":138.3412780761719},"width":606.2812328338623,"sublayerTransform":[1,0,0,0,0,1,0,0,0,0,1,0,0,0,0,1],"contentsRect":{"y":0,"x":0,"width":1,"height":1},"opacity":1,"edgeAntialiasingMask":251658240,"height":55.0000011920929,"hidden":false,"anchorPoint":{"pointX":0.5,"pointY":0.5}},"objectID":"644B9929-5609-4910-9FC5-59D425D82989","layers":[{"animations":[],"initialState":{"affineTransform":[1,0,0,1,0,0],"masksToBounds":false,"rotation":0,"scale":1,"position":{"pointX":507.4467167854309,"pointY":273.1587225198746},"width":606.2812328338623,"sublayerTransform":[1,0,0,0,0,1,0,0,0,0,1,-0.0004922987690640373,0,0,0,1],"contentsRect":{"y":0,"x":0,"width":1,"height":1},"opacity":1,"edgeAntialiasingMask":251658240,"height":55.0000011920929,"hidden":false,"anchorPoint":{"pointX":0.836982392500487,"pointY":4.966522119987615}},"layers":[{"animations":[{"timeOffset":0,"from":{"scalar":true},"beginTime":1e-100,"repeatCount":0,"fillMode":"both","property":"hidden","autoreverses":false,"duration":0.01,"to":{"scalar":false}}],"layers":[],"initialState":{"affineTransform":[1,0,0,1,0,0],"masksToBounds":false,"rotation":0,"scale":1,"position":{"pointX":177.4467167854309,"pointY":29.15872251987457},"width":348,"sublayerTransform":[1,0,0,0,0,1,0,0,0,0,1,0,0,0,0,1],"contentsRect":{"y":0,"x":0,"width":1,"height":1},"opacity":1,"edgeAntialiasingMask":0,"height":40,"hidden":true,"anchorPoint":{"pointX":0.5,"pointY":0.5}},"texture":"A7B691CCA327CFDA5B5EAB08D630A73B"}]}]},"effects":[],"duration":0.01,"type":"buildIn","name":"apple:appear","objectID":"644B9929-5609-4910-9FC5-59D425D82989"}],"automaticPlay":false,"hyperlinks":[],"accessibility":[{"text":"ng-best-practices","targetRectangle":{"y":1.71030580997467,"x":7.553269386291504,"width":526.83125,"height":86}}],"baseLayer":{"animations":[],"initialState":{"affineTransform":[1,0,0,1,0,0],"masksToBounds":false,"rotation":0,"scale":1,"position":{"pointX":512,"pointY":384},"width":1024,"sublayerTransform":[1,0,0,0,0,1,0,0,0,0,1,0,0,0,0,1],"contentsRect":{"y":0,"x":0,"width":1,"height":1},"opacity":1,"edgeAntialiasingMask":251658240,"height":768,"hidden":false,"anchorPoint":{"pointX":0.5,"pointY":0.5}},"layers":[{"animations":[],"initialState":{"affineTransform":[1,0,0,1,0,0],"masksToBounds":false,"rotation":0,"scale":1,"position":{"pointX":512,"pointY":384},"width":1024,"sublayerTransform":[1,0,0,0,0,1,0,0,0,0,1,0,0,0,0,1],"contentsRect":{"y":0,"x":0,"width":1,"height":1},"opacity":1,"edgeAntialiasingMask":251658240,"height":768,"hidden":false,"anchorPoint":{"pointX":0.5,"pointY":0.5}},"layers":[{"animations":[],"initialState":{"affineTransform":[1,0,0,1,0,0],"masksToBounds":false,"rotation":0,"scale":1,"position":{"pointX":512,"pointY":384},"width":1024,"sublayerTransform":[1,0,0,0,0,1,0,0,0,0,1,0,0,0,0,1],"contentsRect":{"y":0,"x":0,"width":1,"height":1},"opacity":1,"edgeAntialiasingMask":251658240,"height":768,"hidden":false,"anchorPoint":{"pointX":0.5,"pointY":0.5}},"layers":[{"animations":[],"layers":[],"initialState":{"affineTransform":[1,0,0,1,0,0],"masksToBounds":false,"rotation":0,"scale":1,"position":{"pointX":512,"pointY":384},"width":1024,"sublayerTransform":[1,0,0,0,0,1,0,0,0,0,1,0,0,0,0,1],"contentsRect":{"y":0,"x":0,"width":1,"height":1},"opacity":1,"edgeAntialiasingMask":0,"height":768,"hidden":false,"anchorPoint":{"pointX":0.5,"pointY":0.5}},"texture":"FBB5DEA59905EE30EF2803B0A74DF992"}]}]},{"animations":[],"initialState":{"affineTransform":[1,0,0,1,0,0],"masksToBounds":false,"rotation":0,"scale":1,"position":{"pointX":512,"pointY":384},"width":1024,"sublayerTransform":[1,0,0,0,0,1,0,0,0,0,1,0,0,0,0,1],"contentsRect":{"y":0,"x":0,"width":1,"height":1},"opacity":1,"edgeAntialiasingMask":251658240,"height":768,"hidden":false,"anchorPoint":{"pointX":0.5,"pointY":0.5}},"layers":[{"animations":[],"initialState":{"affineTransform":[1,0,0,1,0,0],"masksToBounds":false,"rotation":0,"scale":1,"position":{"pointX":307.6939001083374,"pointY":44.95946034789085},"width":606.2812614440918,"sublayerTransform":[1,0,0,0,0,1,0,0,0,0,1,0,0,0,0,1],"contentsRect":{"y":0,"x":0,"width":1,"height":1},"opacity":1,"edgeAntialiasingMask":251658240,"height":92.49830907583237,"hidden":false,"anchorPoint":{"pointX":0.5,"pointY":0.5}},"objectID":"EA471F18-764E-4AEC-8D40-9D8DB699B6A0","layers":[{"animations":[],"layers":[],"initialState":{"affineTransform":[1,0,0,1,0,0],"masksToBounds":false,"rotation":0,"scale":1,"position":{"pointX":267.4467306137085,"pointY":53.28969419002533},"width":524,"sublayerTransform":[1,0,0,0,0,1,0,0,0,0,1,0,0,0,0,1],"contentsRect":{"y":0,"x":0,"width":1,"height":1},"opacity":1,"edgeAntialiasingMask":0,"height":70,"hidden":false,"anchorPoint":{"pointX":0.5,"pointY":0.5}},"texture":"26E1D36A86E033FA4AB154F481E23A88"}]}]},{"animations":[],"initialState":{"affineTransform":[1,0,0,1,0,0],"masksToBounds":false,"rotation":0,"scale":1,"position":{"pointX":512,"pointY":384},"width":1024,"sublayerTransform":[1,0,0,0,0,1,0,0,0,0,1,0,0,0,0,1],"contentsRect":{"y":0,"x":0,"width":1,"height":1},"opacity":1,"edgeAntialiasingMask":251658240,"height":768,"hidden":false,"anchorPoint":{"pointX":0.5,"pointY":0.5}},"layers":[{"animations":[],"initialState":{"affineTransform":[1,0,0,1,0,0],"masksToBounds":false,"rotation":0,"scale":1,"position":{"pointX":520.1402071490811,"pointY":103.0249404907227},"width":1037.232795193777,"sublayerTransform":[1,0,0,0,0,1,0,0,0,0,1,0,0,0,0,1],"contentsRect":{"y":0,"x":0,"width":1,"height":1},"opacity":1,"edgeAntialiasingMask":251658240,"height":1,"hidden":false,"anchorPoint":{"pointX":0.5,"pointY":0.5}},"objectID":"42EE13B2-AC7C-4134-9AC4-A300F252CAD6","layers":[{"animations":[],"layers":[],"initialState":{"affineTransform":[1,0,0,1,0,0],"masksToBounds":false,"rotation":0,"scale":1,"position":{"pointX":518.4761904478073,"pointY":0.4750595092773438},"width":1040,"sublayerTransform":[1,0,0,0,0,1,0,0,0,0,1,0,0,0,0,1],"contentsRect":{"y":0,"x":0,"width":1,"height":1},"opacity":1,"edgeAntialiasingMask":0,"height":4,"hidden":false,"anchorPoint":{"pointX":0.5,"pointY":0.5}},"texture":"15CA13132A771FE1DB043EB28E9335FD"}]}]},{"animations":[],"initialState":{"affineTransform":[1,0,0,1,0,0],"masksToBounds":false,"rotation":0,"scale":1,"position":{"pointX":512,"pointY":384},"width":1024,"sublayerTransform":[1,0,0,0,0,1,0,0,0,0,1,0,0,0,0,1],"contentsRect":{"y":0,"x":0,"width":1,"height":1},"opacity":1,"edgeAntialiasingMask":251658240,"height":768,"hidden":false,"anchorPoint":{"pointX":0.5,"pointY":0.5}},"layers":[{"animations":[],"initialState":{"affineTransform":[1,0,0,1,0,0],"masksToBounds":false,"rotation":0,"scale":1,"position":{"pointX":307.6938996315002,"pointY":138.3412780761719},"width":606.2812328338623,"sublayerTransform":[1,0,0,0,0,1,0,0,0,0,1,0,0,0,0,1],"contentsRect":{"y":0,"x":0,"width":1,"height":1},"opacity":1,"edgeAntialiasingMask":251658240,"height":55.0000011920929,"hidden":false,"anchorPoint":{"pointX":0.5,"pointY":0.5}},"objectID":"644B9929-5609-4910-9FC5-59D425D82989","layers":[{"animations":[],"layers":[],"initialState":{"affineTransform":[1,0,0,1,0,0],"masksToBounds":false,"rotation":0,"scale":1,"position":{"pointX":177.4467167854309,"pointY":29.15872251987457},"width":348,"sublayerTransform":[1,0,0,0,0,1,0,0,0,0,1,0,0,0,0,1],"contentsRect":{"y":0,"x":0,"width":1,"height":1},"opacity":1,"edgeAntialiasingMask":0,"height":40,"hidden":true,"anchorPoint":{"pointX":0.5,"pointY":0.5}},"texture":"A7B691CCA327CFDA5B5EAB08D630A73B"}]}]},{"animations":[],"initialState":{"affineTransform":[1,0,0,1,0,0],"masksToBounds":false,"rotation":0,"scale":1,"position":{"pointX":512,"pointY":384},"width":1024,"sublayerTransform":[1,0,0,0,0,1,0,0,0,0,1,0,0,0,0,1],"contentsRect":{"y":0,"x":0,"width":1,"height":1},"opacity":1,"edgeAntialiasingMask":251658240,"height":768,"hidden":false,"anchorPoint":{"pointX":0.5,"pointY":0.5}},"layers":[{"animations":[],"initialState":{"affineTransform":[1,0,0,1,0,0],"masksToBounds":false,"rotation":0,"scale":1,"position":{"pointX":245.1995741742538,"pointY":467.6576090315758},"width":358.1753730773926,"sublayerTransform":[1,0,0,0,0,1,0,0,0,0,1,0,0,0,0,1],"contentsRect":{"y":0,"x":0,"width":1,"height":1},"opacity":1,"edgeAntialiasingMask":251658240,"height":588.9999866485596,"hidden":false,"anchorPoint":{"pointX":0.5,"pointY":0.5}},"objectID":"8495C19A-0469-4977-ACA8-24C5576C96C1","layers":[{"animations":[],"layers":[],"initialState":{"affineTransform":[1,0,0,1,0,0],"masksToBounds":false,"rotation":0,"scale":1,"position":{"pointX":134.3881123644425,"pointY":294.342384292704},"width":265,"sublayerTransform":[1,0,0,0,0,1,0,0,0,0,1,0,0,0,0,1],"contentsRect":{"y":0,"x":0,"width":1,"height":1},"opacity":1,"edgeAntialiasingMask":0,"height":577,"hidden":true,"anchorPoint":{"pointX":0.5,"pointY":0.5}},"texture":"BFB39CA5157C9F5512005187072B4883"}]}]},{"animations":[],"initialState":{"affineTransform":[1,0,0,1,0,0],"masksToBounds":false,"rotation":0,"scale":1,"position":{"pointX":512,"pointY":384},"width":1024,"sublayerTransform":[1,0,0,0,0,1,0,0,0,0,1,0,0,0,0,1],"contentsRect":{"y":0,"x":0,"width":1,"height":1},"opacity":1,"edgeAntialiasingMask":251658240,"height":768,"hidden":false,"anchorPoint":{"pointX":0.5,"pointY":0.5}},"layers":[{"animations":[],"initialState":{"affineTransform":[1,0,0,1,0,0],"masksToBounds":false,"rotation":0,"scale":1,"position":{"pointX":746.3016124258227,"pointY":287.4172334441252},"width":358.1753730773926,"sublayerTransform":[1,0,0,0,0,1,0,0,0,0,1,0,0,0,0,1],"contentsRect":{"y":0,"x":0,"width":1,"height":1},"opacity":1,"edgeAntialiasingMask":251658240,"height":186.0000014305115,"hidden":false,"anchorPoint":{"pointX":0.5,"pointY":0.5}},"objectID":"DB5ACEF3-8D99-4FDB-9AE0-6AB4A08C9DA2","layers":[{"animations":[],"layers":[],"initialState":{"affineTransform":[1,0,0,1,0,0],"masksToBounds":false,"rotation":0,"scale":1,"position":{"pointX":134.2860741128736,"pointY":92.58276727113054},"width":265,"sublayerTransform":[1,0,0,0,0,1,0,0,0,0,1,0,0,0,0,1],"contentsRect":{"y":0,"x":0,"width":1,"height":1},"opacity":1,"edgeAntialiasingMask":0,"height":174,"hidden":true,"anchorPoint":{"pointX":0.5,"pointY":0.5}},"texture":"5DC4798C72AE6D64ACFE95104A79F431"}]}]},{"animations":[],"initialState":{"affineTransform":[1,0,0,1,0,0],"masksToBounds":false,"rotation":0,"scale":1,"position":{"pointX":512,"pointY":384},"width":1024,"sublayerTransform":[1,0,0,0,0,1,0,0,0,0,1,0,0,0,0,1],"contentsRect":{"y":0,"x":0,"width":1,"height":1},"opacity":1,"edgeAntialiasingMask":251658240,"height":768,"hidden":false,"anchorPoint":{"pointX":0.5,"pointY":0.5}},"layers":[{"animations":[],"initialState":{"affineTransform":[1,0,0,1,0,0],"masksToBounds":false,"rotation":0,"scale":1,"position":{"pointX":733.4557947820554,"pointY":444.9931895349031},"width":495.2638626098632,"sublayerTransform":[1,0,0,0,0,1,0,0,0,0,1,0,0,0,0,1],"contentsRect":{"y":0,"x":0,"width":1,"height":1},"opacity":1,"edgeAntialiasingMask":251658240,"height":72.00000286102295,"hidden":false,"anchorPoint":{"pointX":0.5,"pointY":0.5}},"objectID":"AC29D5C7-A691-4980-86F2-C23558D1B383","layers":[{"animations":[],"layers":[],"initialState":{"affineTransform":[1,0,0,1,0,0],"masksToBounds":false,"rotation":0,"scale":1,"position":{"pointX":243.6761365228762,"pointY":34.00681189560839},"width":483,"sublayerTransform":[1,0,0,0,0,1,0,0,0,0,1,0,0,0,0,1],"contentsRect":{"y":0,"x":0,"width":1,"height":1},"opacity":1,"edgeAntialiasingMask":0,"height":56,"hidden":true,"anchorPoint":{"pointX":0.5,"pointY":0.5}},"texture":"27A4F9539C29228641EB2997E798939E"}]}]}]}},{"effects":[{"beginTime":0,"baseLayer":{"animations":[],"initialState":{"affineTransform":[1,0,0,1,0,0],"masksToBounds":false,"rotation":0,"scale":1,"position":{"pointX":245.1995741742538,"pointY":467.6576090315758},"width":358.1753730773926,"sublayerTransform":[1,0,0,0,0,1,0,0,0,0,1,0,0,0,0,1],"contentsRect":{"y":0,"x":0,"width":1,"height":1},"opacity":1,"edgeAntialiasingMask":251658240,"height":588.9999866485596,"hidden":false,"anchorPoint":{"pointX":0.5,"pointY":0.5}},"objectID":"8495C19A-0469-4977-ACA8-24C5576C96C1","layers":[{"animations":[],"initialState":{"affineTransform":[1,0,0,1,0,0],"masksToBounds":false,"rotation":0,"scale":1,"position":{"pointX":445.8881123644425,"pointY":210.842384292704},"width":358.1753730773926,"sublayerTransform":[1,0,0,0,0,1,0,0,0,0,1,-0.0004922987690640373,0,0,0,1],"contentsRect":{"y":0,"x":0,"width":1,"height":1},"opacity":1,"edgeAntialiasingMask":251658240,"height":588.9999866485596,"hidden":false,"anchorPoint":{"pointX":1.244887688769427,"pointY":0.3579667047064093}},"layers":[{"animations":[{"timeOffset":0,"from":{"scalar":true},"beginTime":1e-100,"repeatCount":0,"fillMode":"both","property":"hidden","autoreverses":false,"duration":0.01,"to":{"scalar":false}}],"layers":[],"initialState":{"affineTransform":[1,0,0,1,0,0],"masksToBounds":false,"rotation":0,"scale":1,"position":{"pointX":134.3881123644425,"pointY":294.342384292704},"width":265,"sublayerTransform":[1,0,0,0,0,1,0,0,0,0,1,0,0,0,0,1],"contentsRect":{"y":0,"x":0,"width":1,"height":1},"opacity":1,"edgeAntialiasingMask":0,"height":577,"hidden":true,"anchorPoint":{"pointX":0.5,"pointY":0.5}},"texture":"BFB39CA5157C9F5512005187072B4883"}]}]},"effects":[],"duration":0.01,"type":"buildIn","name":"apple:appear","objectID":"8495C19A-0469-4977-ACA8-24C5576C96C1"}],"automaticPlay":false,"hyperlinks":[],"accessibility":[{"text":"ng-best-practices","targetRectangle":{"y":1.71030580997467,"x":7.553269386291504,"width":526.83125,"height":86}},{"text":"Use ng-repeat wisely","targetRectangle":{"y":113.8412774801254,"x":7.553283214569092,"width":346.968,"height":49}}],"baseLayer":{"animations":[],"initialState":{"affineTransform":[1,0,0,1,0,0],"masksToBounds":false,"rotation":0,"scale":1,"position":{"pointX":512,"pointY":384},"width":1024,"sublayerTransform":[1,0,0,0,0,1,0,0,0,0,1,0,0,0,0,1],"contentsRect":{"y":0,"x":0,"width":1,"height":1},"opacity":1,"edgeAntialiasingMask":251658240,"height":768,"hidden":false,"anchorPoint":{"pointX":0.5,"pointY":0.5}},"layers":[{"animations":[],"initialState":{"affineTransform":[1,0,0,1,0,0],"masksToBounds":false,"rotation":0,"scale":1,"position":{"pointX":512,"pointY":384},"width":1024,"sublayerTransform":[1,0,0,0,0,1,0,0,0,0,1,0,0,0,0,1],"contentsRect":{"y":0,"x":0,"width":1,"height":1},"opacity":1,"edgeAntialiasingMask":251658240,"height":768,"hidden":false,"anchorPoint":{"pointX":0.5,"pointY":0.5}},"layers":[{"animations":[],"initialState":{"affineTransform":[1,0,0,1,0,0],"masksToBounds":false,"rotation":0,"scale":1,"position":{"pointX":512,"pointY":384},"width":1024,"sublayerTransform":[1,0,0,0,0,1,0,0,0,0,1,0,0,0,0,1],"contentsRect":{"y":0,"x":0,"width":1,"height":1},"opacity":1,"edgeAntialiasingMask":251658240,"height":768,"hidden":false,"anchorPoint":{"pointX":0.5,"pointY":0.5}},"layers":[{"animations":[],"layers":[],"initialState":{"affineTransform":[1,0,0,1,0,0],"masksToBounds":false,"rotation":0,"scale":1,"position":{"pointX":512,"pointY":384},"width":1024,"sublayerTransform":[1,0,0,0,0,1,0,0,0,0,1,0,0,0,0,1],"contentsRect":{"y":0,"x":0,"width":1,"height":1},"opacity":1,"edgeAntialiasingMask":0,"height":768,"hidden":false,"anchorPoint":{"pointX":0.5,"pointY":0.5}},"texture":"FBB5DEA59905EE30EF2803B0A74DF992"}]}]},{"animations":[],"initialState":{"affineTransform":[1,0,0,1,0,0],"masksToBounds":false,"rotation":0,"scale":1,"position":{"pointX":512,"pointY":384},"width":1024,"sublayerTransform":[1,0,0,0,0,1,0,0,0,0,1,0,0,0,0,1],"contentsRect":{"y":0,"x":0,"width":1,"height":1},"opacity":1,"edgeAntialiasingMask":251658240,"height":768,"hidden":false,"anchorPoint":{"pointX":0.5,"pointY":0.5}},"layers":[{"animations":[],"initialState":{"affineTransform":[1,0,0,1,0,0],"masksToBounds":false,"rotation":0,"scale":1,"position":{"pointX":307.6939001083374,"pointY":44.95946034789085},"width":606.2812614440918,"sublayerTransform":[1,0,0,0,0,1,0,0,0,0,1,0,0,0,0,1],"contentsRect":{"y":0,"x":0,"width":1,"height":1},"opacity":1,"edgeAntialiasingMask":251658240,"height":92.49830907583237,"hidden":false,"anchorPoint":{"pointX":0.5,"pointY":0.5}},"objectID":"EA471F18-764E-4AEC-8D40-9D8DB699B6A0","layers":[{"animations":[],"layers":[],"initialState":{"affineTransform":[1,0,0,1,0,0],"masksToBounds":false,"rotation":0,"scale":1,"position":{"pointX":267.4467306137085,"pointY":53.28969419002533},"width":524,"sublayerTransform":[1,0,0,0,0,1,0,0,0,0,1,0,0,0,0,1],"contentsRect":{"y":0,"x":0,"width":1,"height":1},"opacity":1,"edgeAntialiasingMask":0,"height":70,"hidden":false,"anchorPoint":{"pointX":0.5,"pointY":0.5}},"texture":"26E1D36A86E033FA4AB154F481E23A88"}]}]},{"animations":[],"initialState":{"affineTransform":[1,0,0,1,0,0],"masksToBounds":false,"rotation":0,"scale":1,"position":{"pointX":512,"pointY":384},"width":1024,"sublayerTransform":[1,0,0,0,0,1,0,0,0,0,1,0,0,0,0,1],"contentsRect":{"y":0,"x":0,"width":1,"height":1},"opacity":1,"edgeAntialiasingMask":251658240,"height":768,"hidden":false,"anchorPoint":{"pointX":0.5,"pointY":0.5}},"layers":[{"animations":[],"initialState":{"affineTransform":[1,0,0,1,0,0],"masksToBounds":false,"rotation":0,"scale":1,"position":{"pointX":520.1402071490811,"pointY":103.0249404907227},"width":1037.232795193777,"sublayerTransform":[1,0,0,0,0,1,0,0,0,0,1,0,0,0,0,1],"contentsRect":{"y":0,"x":0,"width":1,"height":1},"opacity":1,"edgeAntialiasingMask":251658240,"height":1,"hidden":false,"anchorPoint":{"pointX":0.5,"pointY":0.5}},"objectID":"42EE13B2-AC7C-4134-9AC4-A300F252CAD6","layers":[{"animations":[],"layers":[],"initialState":{"affineTransform":[1,0,0,1,0,0],"masksToBounds":false,"rotation":0,"scale":1,"position":{"pointX":518.4761904478073,"pointY":0.4750595092773438},"width":1040,"sublayerTransform":[1,0,0,0,0,1,0,0,0,0,1,0,0,0,0,1],"contentsRect":{"y":0,"x":0,"width":1,"height":1},"opacity":1,"edgeAntialiasingMask":0,"height":4,"hidden":false,"anchorPoint":{"pointX":0.5,"pointY":0.5}},"texture":"15CA13132A771FE1DB043EB28E9335FD"}]}]},{"animations":[],"initialState":{"affineTransform":[1,0,0,1,0,0],"masksToBounds":false,"rotation":0,"scale":1,"position":{"pointX":512,"pointY":384},"width":1024,"sublayerTransform":[1,0,0,0,0,1,0,0,0,0,1,0,0,0,0,1],"contentsRect":{"y":0,"x":0,"width":1,"height":1},"opacity":1,"edgeAntialiasingMask":251658240,"height":768,"hidden":false,"anchorPoint":{"pointX":0.5,"pointY":0.5}},"layers":[{"animations":[],"initialState":{"affineTransform":[1,0,0,1,0,0],"masksToBounds":false,"rotation":0,"scale":1,"position":{"pointX":307.6938996315002,"pointY":138.3412780761719},"width":606.2812328338623,"sublayerTransform":[1,0,0,0,0,1,0,0,0,0,1,0,0,0,0,1],"contentsRect":{"y":0,"x":0,"width":1,"height":1},"opacity":1,"edgeAntialiasingMask":251658240,"height":55.0000011920929,"hidden":false,"anchorPoint":{"pointX":0.5,"pointY":0.5}},"objectID":"644B9929-5609-4910-9FC5-59D425D82989","layers":[{"animations":[],"layers":[],"initialState":{"affineTransform":[1,0,0,1,0,0],"masksToBounds":false,"rotation":0,"scale":1,"position":{"pointX":177.4467167854309,"pointY":29.15872251987457},"width":348,"sublayerTransform":[1,0,0,0,0,1,0,0,0,0,1,0,0,0,0,1],"contentsRect":{"y":0,"x":0,"width":1,"height":1},"opacity":1,"edgeAntialiasingMask":0,"height":40,"hidden":false,"anchorPoint":{"pointX":0.5,"pointY":0.5}},"texture":"A7B691CCA327CFDA5B5EAB08D630A73B"}]}]},{"animations":[],"initialState":{"affineTransform":[1,0,0,1,0,0],"masksToBounds":false,"rotation":0,"scale":1,"position":{"pointX":512,"pointY":384},"width":1024,"sublayerTransform":[1,0,0,0,0,1,0,0,0,0,1,0,0,0,0,1],"contentsRect":{"y":0,"x":0,"width":1,"height":1},"opacity":1,"edgeAntialiasingMask":251658240,"height":768,"hidden":false,"anchorPoint":{"pointX":0.5,"pointY":0.5}},"layers":[{"animations":[],"initialState":{"affineTransform":[1,0,0,1,0,0],"masksToBounds":false,"rotation":0,"scale":1,"position":{"pointX":245.1995741742538,"pointY":467.6576090315758},"width":358.1753730773926,"sublayerTransform":[1,0,0,0,0,1,0,0,0,0,1,0,0,0,0,1],"contentsRect":{"y":0,"x":0,"width":1,"height":1},"opacity":1,"edgeAntialiasingMask":251658240,"height":588.9999866485596,"hidden":false,"anchorPoint":{"pointX":0.5,"pointY":0.5}},"objectID":"8495C19A-0469-4977-ACA8-24C5576C96C1","layers":[{"animations":[],"layers":[],"initialState":{"affineTransform":[1,0,0,1,0,0],"masksToBounds":false,"rotation":0,"scale":1,"position":{"pointX":134.3881123644425,"pointY":294.342384292704},"width":265,"sublayerTransform":[1,0,0,0,0,1,0,0,0,0,1,0,0,0,0,1],"contentsRect":{"y":0,"x":0,"width":1,"height":1},"opacity":1,"edgeAntialiasingMask":0,"height":577,"hidden":true,"anchorPoint":{"pointX":0.5,"pointY":0.5}},"texture":"BFB39CA5157C9F5512005187072B4883"}]}]},{"animations":[],"initialState":{"affineTransform":[1,0,0,1,0,0],"masksToBounds":false,"rotation":0,"scale":1,"position":{"pointX":512,"pointY":384},"width":1024,"sublayerTransform":[1,0,0,0,0,1,0,0,0,0,1,0,0,0,0,1],"contentsRect":{"y":0,"x":0,"width":1,"height":1},"opacity":1,"edgeAntialiasingMask":251658240,"height":768,"hidden":false,"anchorPoint":{"pointX":0.5,"pointY":0.5}},"layers":[{"animations":[],"initialState":{"affineTransform":[1,0,0,1,0,0],"masksToBounds":false,"rotation":0,"scale":1,"position":{"pointX":746.3016124258227,"pointY":287.4172334441252},"width":358.1753730773926,"sublayerTransform":[1,0,0,0,0,1,0,0,0,0,1,0,0,0,0,1],"contentsRect":{"y":0,"x":0,"width":1,"height":1},"opacity":1,"edgeAntialiasingMask":251658240,"height":186.0000014305115,"hidden":false,"anchorPoint":{"pointX":0.5,"pointY":0.5}},"objectID":"DB5ACEF3-8D99-4FDB-9AE0-6AB4A08C9DA2","layers":[{"animations":[],"layers":[],"initialState":{"affineTransform":[1,0,0,1,0,0],"masksToBounds":false,"rotation":0,"scale":1,"position":{"pointX":134.2860741128736,"pointY":92.58276727113054},"width":265,"sublayerTransform":[1,0,0,0,0,1,0,0,0,0,1,0,0,0,0,1],"contentsRect":{"y":0,"x":0,"width":1,"height":1},"opacity":1,"edgeAntialiasingMask":0,"height":174,"hidden":true,"anchorPoint":{"pointX":0.5,"pointY":0.5}},"texture":"5DC4798C72AE6D64ACFE95104A79F431"}]}]},{"animations":[],"initialState":{"affineTransform":[1,0,0,1,0,0],"masksToBounds":false,"rotation":0,"scale":1,"position":{"pointX":512,"pointY":384},"width":1024,"sublayerTransform":[1,0,0,0,0,1,0,0,0,0,1,0,0,0,0,1],"contentsRect":{"y":0,"x":0,"width":1,"height":1},"opacity":1,"edgeAntialiasingMask":251658240,"height":768,"hidden":false,"anchorPoint":{"pointX":0.5,"pointY":0.5}},"layers":[{"animations":[],"initialState":{"affineTransform":[1,0,0,1,0,0],"masksToBounds":false,"rotation":0,"scale":1,"position":{"pointX":733.4557947820554,"pointY":444.9931895349031},"width":495.2638626098632,"sublayerTransform":[1,0,0,0,0,1,0,0,0,0,1,0,0,0,0,1],"contentsRect":{"y":0,"x":0,"width":1,"height":1},"opacity":1,"edgeAntialiasingMask":251658240,"height":72.00000286102295,"hidden":false,"anchorPoint":{"pointX":0.5,"pointY":0.5}},"objectID":"AC29D5C7-A691-4980-86F2-C23558D1B383","layers":[{"animations":[],"layers":[],"initialState":{"affineTransform":[1,0,0,1,0,0],"masksToBounds":false,"rotation":0,"scale":1,"position":{"pointX":243.6761365228762,"pointY":34.00681189560839},"width":483,"sublayerTransform":[1,0,0,0,0,1,0,0,0,0,1,0,0,0,0,1],"contentsRect":{"y":0,"x":0,"width":1,"height":1},"opacity":1,"edgeAntialiasingMask":0,"height":56,"hidden":true,"anchorPoint":{"pointX":0.5,"pointY":0.5}},"texture":"27A4F9539C29228641EB2997E798939E"}]}]}]}},{"effects":[{"beginTime":0,"baseLayer":{"animations":[],"initialState":{"affineTransform":[1,0,0,1,0,0],"masksToBounds":false,"rotation":0,"scale":1,"position":{"pointX":746.3016124258227,"pointY":287.4172334441252},"width":358.1753730773926,"sublayerTransform":[1,0,0,0,0,1,0,0,0,0,1,0,0,0,0,1],"contentsRect":{"y":0,"x":0,"width":1,"height":1},"opacity":1,"edgeAntialiasingMask":251658240,"height":186.0000014305115,"hidden":false,"anchorPoint":{"pointX":0.5,"pointY":0.5}},"objectID":"DB5ACEF3-8D99-4FDB-9AE0-6AB4A08C9DA2","layers":[{"animations":[],"initialState":{"affineTransform":[1,0,0,1,0,0],"masksToBounds":false,"rotation":0,"scale":1,"position":{"pointX":-55.21392588712638,"pointY":189.5827672711305},"width":358.1753730773926,"sublayerTransform":[1,0,0,0,0,1,0,0,0,0,1,-0.0004922987690640373,0,0,0,1],"contentsRect":{"y":0,"x":0,"width":1,"height":1},"opacity":1,"edgeAntialiasingMask":251658240,"height":186.0000014305115,"hidden":false,"anchorPoint":{"pointX":-0.1541533283339278,"pointY":1.019262181790668}},"layers":[{"animations":[{"timeOffset":0,"from":{"scalar":true},"beginTime":1e-100,"repeatCount":0,"fillMode":"both","property":"hidden","autoreverses":false,"duration":0.01,"to":{"scalar":false}}],"layers":[],"initialState":{"affineTransform":[1,0,0,1,0,0],"masksToBounds":false,"rotation":0,"scale":1,"position":{"pointX":134.2860741128736,"pointY":92.58276727113054},"width":265,"sublayerTransform":[1,0,0,0,0,1,0,0,0,0,1,0,0,0,0,1],"contentsRect":{"y":0,"x":0,"width":1,"height":1},"opacity":1,"edgeAntialiasingMask":0,"height":174,"hidden":true,"anchorPoint":{"pointX":0.5,"pointY":0.5}},"texture":"5DC4798C72AE6D64ACFE95104A79F431"}]}]},"effects":[],"duration":0.01,"type":"buildIn","name":"apple:appear","objectID":"DB5ACEF3-8D99-4FDB-9AE0-6AB4A08C9DA2"},{"beginTime":0,"baseLayer":{"animations":[],"initialState":{"affineTransform":[1,0,0,1,0,0],"masksToBounds":false,"rotation":0,"scale":1,"position":{"pointX":733.4557947820554,"pointY":444.9931895349031},"width":495.2638626098632,"sublayerTransform":[1,0,0,0,0,1,0,0,0,0,1,0,0,0,0,1],"contentsRect":{"y":0,"x":0,"width":1,"height":1},"opacity":1,"edgeAntialiasingMask":251658240,"height":72.00000286102295,"hidden":false,"anchorPoint":{"pointX":0.5,"pointY":0.5}},"objectID":"AC29D5C7-A691-4980-86F2-C23558D1B383","layers":[{"animations":[],"initialState":{"affineTransform":[1,0,0,1,0,0],"masksToBounds":false,"rotation":0,"scale":1,"position":{"pointX":26.17613652287628,"pointY":-24.99318810439161},"width":495.2638626098632,"sublayerTransform":[1,0,0,0,0,1,0,0,0,0,1,-0.0004922987690640373,0,0,0,1],"contentsRect":{"y":0,"x":0,"width":1,"height":1},"opacity":1,"edgeAntialiasingMask":251658240,"height":72.00000286102295,"hidden":false,"anchorPoint":{"pointX":0.05285291033538649,"pointY":-0.3471275987673831}},"layers":[{"animations":[{"timeOffset":0,"from":{"scalar":true},"beginTime":1e-100,"repeatCount":0,"fillMode":"both","property":"hidden","autoreverses":false,"duration":0.01,"to":{"scalar":false}}],"layers":[],"initialState":{"affineTransform":[1,0,0,1,0,0],"masksToBounds":false,"rotation":0,"scale":1,"position":{"pointX":243.6761365228762,"pointY":34.00681189560839},"width":483,"sublayerTransform":[1,0,0,0,0,1,0,0,0,0,1,0,0,0,0,1],"contentsRect":{"y":0,"x":0,"width":1,"height":1},"opacity":1,"edgeAntialiasingMask":0,"height":56,"hidden":true,"anchorPoint":{"pointX":0.5,"pointY":0.5}},"texture":"27A4F9539C29228641EB2997E798939E"}]}]},"effects":[],"duration":0.01,"type":"buildIn","name":"apple:appear","objectID":"AC29D5C7-A691-4980-86F2-C23558D1B383"}],"automaticPlay":false,"hyperlinks":[],"accessibility":[{"text":"ng-best-practices","targetRectangle":{"y":1.71030580997467,"x":7.553269386291504,"width":526.83125,"height":86}},{"text":"Use ng-repeat wisely","targetRectangle":{"y":113.8412774801254,"x":7.553283214569092,"width":346.968,"height":49}},{"text":"<ul ng-controller=\"ListCtrl\">","targetRectangle":{"y":176.157615707296,"x":69.11188763555752,"width":235.728,"height":31}},{"text":"  <li ng-repeat=\"item in items\">","targetRectangle":{"y":207.157615707296,"x":69.11188763555752,"width":261.126,"height":31}},{"text":"    <div ng-if=“$index == 0”>","targetRectangle":{"y":238.157615707296,"x":69.11188763555752,"width":237.114,"height":31}},{"text":"      …do something…","targetRectangle":{"y":269.157615707296,"x":69.11188763555752,"width":177.84,"height":31}},{"text":"    </div>","targetRectangle":{"y":300.157615707296,"x":69.11188763555752,"width":73.98,"height":31}},{"text":"    <div ng-if=“$index == 1”>","targetRectangle":{"y":331.157615707296,"x":69.11188763555752,"width":237.114,"height":31}},{"text":"      …do another thing…","targetRectangle":{"y":362.157615707296,"x":69.11188763555752,"width":201.564,"height":31}},{"text":"    </div>","targetRectangle":{"y":393.157615707296,"x":69.11188763555752,"width":73.98,"height":31}},{"text":"    <div ng-if=“$index == 3”>","targetRectangle":{"y":424.157615707296,"x":69.11188763555752,"width":237.114,"height":31}},{"text":"      …do whatever…","targetRectangle":{"y":455.157615707296,"x":69.11188763555752,"width":164.916,"height":31}},{"text":"    </div>","targetRectangle":{"y":486.157615707296,"x":69.11188763555752,"width":73.98,"height":31}},{"text":"   <div ng-if=“$last”>","targetRectangle":{"y":517.157615707296,"x":69.11188763555752,"width":171.81,"height":31}},{"text":"      …do this…","targetRectangle":{"y":548.157615707296,"x":69.11188763555752,"width":118.728,"height":31}},{"text":"    </div>","targetRectangle":{"y":579.157615707296,"x":69.11188763555752,"width":73.98,"height":31}},{"text":"    <div>","targetRectangle":{"y":610.157615707296,"x":69.11188763555752,"width":67.14,"height":31}},{"text":"      …do anything else…","targetRectangle":{"y":641.157615707296,"x":69.11188763555752,"width":199.692,"height":31}},{"text":"    </div>","targetRectangle":{"y":672.157615707296,"x":69.11188763555752,"width":73.98,"height":31}},{"text":"  </li>","targetRectangle":{"y":703.157615707296,"x":69.11188763555752,"width":49.158,"height":31}},{"text":"</ul>","targetRectangle":{"y":734.157615707296,"x":69.11188763555752,"width":45.97199999999999,"height":25}}],"baseLayer":{"animations":[],"initialState":{"affineTransform":[1,0,0,1,0,0],"masksToBounds":false,"rotation":0,"scale":1,"position":{"pointX":512,"pointY":384},"width":1024,"sublayerTransform":[1,0,0,0,0,1,0,0,0,0,1,0,0,0,0,1],"contentsRect":{"y":0,"x":0,"width":1,"height":1},"opacity":1,"edgeAntialiasingMask":251658240,"height":768,"hidden":false,"anchorPoint":{"pointX":0.5,"pointY":0.5}},"layers":[{"animations":[],"initialState":{"affineTransform":[1,0,0,1,0,0],"masksToBounds":false,"rotation":0,"scale":1,"position":{"pointX":512,"pointY":384},"width":1024,"sublayerTransform":[1,0,0,0,0,1,0,0,0,0,1,0,0,0,0,1],"contentsRect":{"y":0,"x":0,"width":1,"height":1},"opacity":1,"edgeAntialiasingMask":251658240,"height":768,"hidden":false,"anchorPoint":{"pointX":0.5,"pointY":0.5}},"layers":[{"animations":[],"initialState":{"affineTransform":[1,0,0,1,0,0],"masksToBounds":false,"rotation":0,"scale":1,"position":{"pointX":512,"pointY":384},"width":1024,"sublayerTransform":[1,0,0,0,0,1,0,0,0,0,1,0,0,0,0,1],"contentsRect":{"y":0,"x":0,"width":1,"height":1},"opacity":1,"edgeAntialiasingMask":251658240,"height":768,"hidden":false,"anchorPoint":{"pointX":0.5,"pointY":0.5}},"layers":[{"animations":[],"layers":[],"initialState":{"affineTransform":[1,0,0,1,0,0],"masksToBounds":false,"rotation":0,"scale":1,"position":{"pointX":512,"pointY":384},"width":1024,"sublayerTransform":[1,0,0,0,0,1,0,0,0,0,1,0,0,0,0,1],"contentsRect":{"y":0,"x":0,"width":1,"height":1},"opacity":1,"edgeAntialiasingMask":0,"height":768,"hidden":false,"anchorPoint":{"pointX":0.5,"pointY":0.5}},"texture":"FBB5DEA59905EE30EF2803B0A74DF992"}]}]},{"animations":[],"initialState":{"affineTransform":[1,0,0,1,0,0],"masksToBounds":false,"rotation":0,"scale":1,"position":{"pointX":512,"pointY":384},"width":1024,"sublayerTransform":[1,0,0,0,0,1,0,0,0,0,1,0,0,0,0,1],"contentsRect":{"y":0,"x":0,"width":1,"height":1},"opacity":1,"edgeAntialiasingMask":251658240,"height":768,"hidden":false,"anchorPoint":{"pointX":0.5,"pointY":0.5}},"layers":[{"animations":[],"initialState":{"affineTransform":[1,0,0,1,0,0],"masksToBounds":false,"rotation":0,"scale":1,"position":{"pointX":307.6939001083374,"pointY":44.95946034789085},"width":606.2812614440918,"sublayerTransform":[1,0,0,0,0,1,0,0,0,0,1,0,0,0,0,1],"contentsRect":{"y":0,"x":0,"width":1,"height":1},"opacity":1,"edgeAntialiasingMask":251658240,"height":92.49830907583237,"hidden":false,"anchorPoint":{"pointX":0.5,"pointY":0.5}},"objectID":"EA471F18-764E-4AEC-8D40-9D8DB699B6A0","layers":[{"animations":[],"layers":[],"initialState":{"affineTransform":[1,0,0,1,0,0],"masksToBounds":false,"rotation":0,"scale":1,"position":{"pointX":267.4467306137085,"pointY":53.28969419002533},"width":524,"sublayerTransform":[1,0,0,0,0,1,0,0,0,0,1,0,0,0,0,1],"contentsRect":{"y":0,"x":0,"width":1,"height":1},"opacity":1,"edgeAntialiasingMask":0,"height":70,"hidden":false,"anchorPoint":{"pointX":0.5,"pointY":0.5}},"texture":"26E1D36A86E033FA4AB154F481E23A88"}]}]},{"animations":[],"initialState":{"affineTransform":[1,0,0,1,0,0],"masksToBounds":false,"rotation":0,"scale":1,"position":{"pointX":512,"pointY":384},"width":1024,"sublayerTransform":[1,0,0,0,0,1,0,0,0,0,1,0,0,0,0,1],"contentsRect":{"y":0,"x":0,"width":1,"height":1},"opacity":1,"edgeAntialiasingMask":251658240,"height":768,"hidden":false,"anchorPoint":{"pointX":0.5,"pointY":0.5}},"layers":[{"animations":[],"initialState":{"affineTransform":[1,0,0,1,0,0],"masksToBounds":false,"rotation":0,"scale":1,"position":{"pointX":520.1402071490811,"pointY":103.0249404907227},"width":1037.232795193777,"sublayerTransform":[1,0,0,0,0,1,0,0,0,0,1,0,0,0,0,1],"contentsRect":{"y":0,"x":0,"width":1,"height":1},"opacity":1,"edgeAntialiasingMask":251658240,"height":1,"hidden":false,"anchorPoint":{"pointX":0.5,"pointY":0.5}},"objectID":"42EE13B2-AC7C-4134-9AC4-A300F252CAD6","layers":[{"animations":[],"layers":[],"initialState":{"affineTransform":[1,0,0,1,0,0],"masksToBounds":false,"rotation":0,"scale":1,"position":{"pointX":518.4761904478073,"pointY":0.4750595092773438},"width":1040,"sublayerTransform":[1,0,0,0,0,1,0,0,0,0,1,0,0,0,0,1],"contentsRect":{"y":0,"x":0,"width":1,"height":1},"opacity":1,"edgeAntialiasingMask":0,"height":4,"hidden":false,"anchorPoint":{"pointX":0.5,"pointY":0.5}},"texture":"15CA13132A771FE1DB043EB28E9335FD"}]}]},{"animations":[],"initialState":{"affineTransform":[1,0,0,1,0,0],"masksToBounds":false,"rotation":0,"scale":1,"position":{"pointX":512,"pointY":384},"width":1024,"sublayerTransform":[1,0,0,0,0,1,0,0,0,0,1,0,0,0,0,1],"contentsRect":{"y":0,"x":0,"width":1,"height":1},"opacity":1,"edgeAntialiasingMask":251658240,"height":768,"hidden":false,"anchorPoint":{"pointX":0.5,"pointY":0.5}},"layers":[{"animations":[],"initialState":{"affineTransform":[1,0,0,1,0,0],"masksToBounds":false,"rotation":0,"scale":1,"position":{"pointX":307.6938996315002,"pointY":138.3412780761719},"width":606.2812328338623,"sublayerTransform":[1,0,0,0,0,1,0,0,0,0,1,0,0,0,0,1],"contentsRect":{"y":0,"x":0,"width":1,"height":1},"opacity":1,"edgeAntialiasingMask":251658240,"height":55.0000011920929,"hidden":false,"anchorPoint":{"pointX":0.5,"pointY":0.5}},"objectID":"644B9929-5609-4910-9FC5-59D425D82989","layers":[{"animations":[],"layers":[],"initialState":{"affineTransform":[1,0,0,1,0,0],"masksToBounds":false,"rotation":0,"scale":1,"position":{"pointX":177.4467167854309,"pointY":29.15872251987457},"width":348,"sublayerTransform":[1,0,0,0,0,1,0,0,0,0,1,0,0,0,0,1],"contentsRect":{"y":0,"x":0,"width":1,"height":1},"opacity":1,"edgeAntialiasingMask":0,"height":40,"hidden":false,"anchorPoint":{"pointX":0.5,"pointY":0.5}},"texture":"A7B691CCA327CFDA5B5EAB08D630A73B"}]}]},{"animations":[],"initialState":{"affineTransform":[1,0,0,1,0,0],"masksToBounds":false,"rotation":0,"scale":1,"position":{"pointX":512,"pointY":384},"width":1024,"sublayerTransform":[1,0,0,0,0,1,0,0,0,0,1,0,0,0,0,1],"contentsRect":{"y":0,"x":0,"width":1,"height":1},"opacity":1,"edgeAntialiasingMask":251658240,"height":768,"hidden":false,"anchorPoint":{"pointX":0.5,"pointY":0.5}},"layers":[{"animations":[],"initialState":{"affineTransform":[1,0,0,1,0,0],"masksToBounds":false,"rotation":0,"scale":1,"position":{"pointX":245.1995741742538,"pointY":467.6576090315758},"width":358.1753730773926,"sublayerTransform":[1,0,0,0,0,1,0,0,0,0,1,0,0,0,0,1],"contentsRect":{"y":0,"x":0,"width":1,"height":1},"opacity":1,"edgeAntialiasingMask":251658240,"height":588.9999866485596,"hidden":false,"anchorPoint":{"pointX":0.5,"pointY":0.5}},"objectID":"8495C19A-0469-4977-ACA8-24C5576C96C1","layers":[{"animations":[],"layers":[],"initialState":{"affineTransform":[1,0,0,1,0,0],"masksToBounds":false,"rotation":0,"scale":1,"position":{"pointX":134.3881123644425,"pointY":294.342384292704},"width":265,"sublayerTransform":[1,0,0,0,0,1,0,0,0,0,1,0,0,0,0,1],"contentsRect":{"y":0,"x":0,"width":1,"height":1},"opacity":1,"edgeAntialiasingMask":0,"height":577,"hidden":false,"anchorPoint":{"pointX":0.5,"pointY":0.5}},"texture":"BFB39CA5157C9F5512005187072B4883"}]}]},{"animations":[],"initialState":{"affineTransform":[1,0,0,1,0,0],"masksToBounds":false,"rotation":0,"scale":1,"position":{"pointX":512,"pointY":384},"width":1024,"sublayerTransform":[1,0,0,0,0,1,0,0,0,0,1,0,0,0,0,1],"contentsRect":{"y":0,"x":0,"width":1,"height":1},"opacity":1,"edgeAntialiasingMask":251658240,"height":768,"hidden":false,"anchorPoint":{"pointX":0.5,"pointY":0.5}},"layers":[{"animations":[],"initialState":{"affineTransform":[1,0,0,1,0,0],"masksToBounds":false,"rotation":0,"scale":1,"position":{"pointX":746.3016124258227,"pointY":287.4172334441252},"width":358.1753730773926,"sublayerTransform":[1,0,0,0,0,1,0,0,0,0,1,0,0,0,0,1],"contentsRect":{"y":0,"x":0,"width":1,"height":1},"opacity":1,"edgeAntialiasingMask":251658240,"height":186.0000014305115,"hidden":false,"anchorPoint":{"pointX":0.5,"pointY":0.5}},"objectID":"DB5ACEF3-8D99-4FDB-9AE0-6AB4A08C9DA2","layers":[{"animations":[],"layers":[],"initialState":{"affineTransform":[1,0,0,1,0,0],"masksToBounds":false,"rotation":0,"scale":1,"position":{"pointX":134.2860741128736,"pointY":92.58276727113054},"width":265,"sublayerTransform":[1,0,0,0,0,1,0,0,0,0,1,0,0,0,0,1],"contentsRect":{"y":0,"x":0,"width":1,"height":1},"opacity":1,"edgeAntialiasingMask":0,"height":174,"hidden":true,"anchorPoint":{"pointX":0.5,"pointY":0.5}},"texture":"5DC4798C72AE6D64ACFE95104A79F431"}]}]},{"animations":[],"initialState":{"affineTransform":[1,0,0,1,0,0],"masksToBounds":false,"rotation":0,"scale":1,"position":{"pointX":512,"pointY":384},"width":1024,"sublayerTransform":[1,0,0,0,0,1,0,0,0,0,1,0,0,0,0,1],"contentsRect":{"y":0,"x":0,"width":1,"height":1},"opacity":1,"edgeAntialiasingMask":251658240,"height":768,"hidden":false,"anchorPoint":{"pointX":0.5,"pointY":0.5}},"layers":[{"animations":[],"initialState":{"affineTransform":[1,0,0,1,0,0],"masksToBounds":false,"rotation":0,"scale":1,"position":{"pointX":733.4557947820554,"pointY":444.9931895349031},"width":495.2638626098632,"sublayerTransform":[1,0,0,0,0,1,0,0,0,0,1,0,0,0,0,1],"contentsRect":{"y":0,"x":0,"width":1,"height":1},"opacity":1,"edgeAntialiasingMask":251658240,"height":72.00000286102295,"hidden":false,"anchorPoint":{"pointX":0.5,"pointY":0.5}},"objectID":"AC29D5C7-A691-4980-86F2-C23558D1B383","layers":[{"animations":[],"layers":[],"initialState":{"affineTransform":[1,0,0,1,0,0],"masksToBounds":false,"rotation":0,"scale":1,"position":{"pointX":243.6761365228762,"pointY":34.00681189560839},"width":483,"sublayerTransform":[1,0,0,0,0,1,0,0,0,0,1,0,0,0,0,1],"contentsRect":{"y":0,"x":0,"width":1,"height":1},"opacity":1,"edgeAntialiasingMask":0,"height":56,"hidden":true,"anchorPoint":{"pointX":0.5,"pointY":0.5}},"texture":"27A4F9539C29228641EB2997E798939E"}]}]}]}},{"effects":[{"beginTime":0,"baseLayer":{"animations":[],"initialState":{"affineTransform":[1,0,0,1,0,0],"masksToBounds":false,"rotation":0,"scale":1,"position":{"pointX":512,"pointY":384},"width":1024,"sublayerTransform":[1,0,0,0,0,1,0,0,0,0,1,0,0,0,0,1],"contentsRect":{"y":0,"x":0,"width":1,"height":1},"opacity":1,"edgeAntialiasingMask":251658240,"height":768,"hidden":false,"anchorPoint":{"pointX":0.5,"pointY":0.5}},"objectID":"0","layers":[{"animations":[],"initialState":{"affineTransform":[1,0,0,1,0,0],"masksToBounds":false,"rotation":0,"scale":1,"position":{"pointX":512,"pointY":384},"width":1024,"sublayerTransform":[1,0,0,0,0,1,0,0,0,0,1,-0.0004922987690640373,0,0,0,1],"contentsRect":{"y":0,"x":0,"width":1,"height":1},"opacity":1,"edgeAntialiasingMask":251658240,"height":768,"hidden":false,"anchorPoint":{"pointX":0.5,"pointY":0.5}},"layers":[{"animations":[],"layers":[],"initialState":{"affineTransform":[1,0,0,1,0,0],"masksToBounds":false,"rotation":0,"scale":1,"position":{"pointX":512,"pointY":384},"width":1024,"sublayerTransform":[1,0,0,0,0,1,0,0,0,0,1,0,0,0,0,1],"contentsRect":{"y":0,"x":0,"width":1,"height":1},"opacity":1,"edgeAntialiasingMask":0,"height":768,"hidden":false,"anchorPoint":{"pointX":0.5,"pointY":0.5}},"texture":"C31DA9B4D76CAB45EBF603B063E74579"},{"animations":[{"timeOffset":0,"from":{"scalar":false},"beginTime":0,"repeatCount":0,"fillMode":"both","property":"hidden","autoreverses":false,"duration":0.01,"to":{"scalar":true}}],"layers":[],"initialState":{"affineTransform":[1,0,0,1,0,0],"masksToBounds":false,"rotation":0,"scale":1,"position":{"pointX":512,"pointY":384},"width":1024,"sublayerTransform":[1,0,0,0,0,1,0,0,0,0,1,0,0,0,0,1],"contentsRect":{"y":0,"x":0,"width":1,"height":1},"opacity":1,"edgeAntialiasingMask":0,"height":768,"hidden":false,"anchorPoint":{"pointX":0.5,"pointY":0.5}},"texture":"B3B9AA996F79885C6FAB5E6D0A29C9E9"}]}]},"effects":[],"duration":0.01,"type":"transition","name":"none","objectID":"0"}],"automaticPlay":false,"hyperlinks":[],"accessibility":[{"text":"ng-best-practices","targetRectangle":{"y":1.71030580997467,"x":7.553269386291504,"width":526.83125,"height":86}},{"text":"<ul ng-controller=\"ListCtrl\">","targetRectangle":{"y":197.4172327288695,"x":570.2139258871264,"width":235.728,"height":31}},{"text":"  <li ng-repeat=\"item in items\">","targetRectangle":{"y":228.4172327288695,"x":570.2139258871264,"width":261.126,"height":31}},{"text":"<format-item item=“item”>","targetRectangle":{"y":259.4172327288695,"x":588.2139258871264,"width":226.692,"height":31}},{"text":"</format-item> ","targetRectangle":{"y":290.4172327288695,"x":588.2139258871264,"width":132.48,"height":31}},{"text":"  </li>","targetRectangle":{"y":321.4172327288695,"x":570.2139258871264,"width":49.15800000000002,"height":31}},{"text":"</ul>","targetRectangle":{"y":352.4172327288695,"x":570.2139258871264,"width":45.97199999999998,"height":25}},{"text":"Use ng-repeat wisely","targetRectangle":{"y":113.8412774801254,"x":7.553283214569092,"width":346.968,"height":49}},{"text":"<ul ng-controller=\"ListCtrl\">","targetRectangle":{"y":176.157615707296,"x":69.11188763555752,"width":235.728,"height":31}},{"text":"  <li ng-repeat=\"item in items\">","targetRectangle":{"y":207.157615707296,"x":69.11188763555752,"width":261.126,"height":31}},{"text":"    <div ng-if=“$index == 0”>","targetRectangle":{"y":238.157615707296,"x":69.11188763555752,"width":237.114,"height":31}},{"text":"      …do something…","targetRectangle":{"y":269.157615707296,"x":69.11188763555752,"width":177.84,"height":31}},{"text":"    </div>","targetRectangle":{"y":300.157615707296,"x":69.11188763555752,"width":73.98,"height":31}},{"text":"    <div ng-if=“$index == 1”>","targetRectangle":{"y":331.157615707296,"x":69.11188763555752,"width":237.114,"height":31}},{"text":"      …do another thing…","targetRectangle":{"y":362.157615707296,"x":69.11188763555752,"width":201.564,"height":31}},{"text":"    </div>","targetRectangle":{"y":393.157615707296,"x":69.11188763555752,"width":73.98,"height":31}},{"text":"    <div ng-if=“$index == 3”>","targetRectangle":{"y":424.157615707296,"x":69.11188763555752,"width":237.114,"height":31}},{"text":"      …do whatever…","targetRectangle":{"y":455.157615707296,"x":69.11188763555752,"width":164.916,"height":31}},{"text":"    </div>","targetRectangle":{"y":486.157615707296,"x":69.11188763555752,"width":73.98,"height":31}},{"text":"   <div ng-if=“$last”>","targetRectangle":{"y":517.157615707296,"x":69.11188763555752,"width":171.81,"height":31}},{"text":"      …do this…","targetRectangle":{"y":548.157615707296,"x":69.11188763555752,"width":118.728,"height":31}},{"text":"    </div>","targetRectangle":{"y":579.157615707296,"x":69.11188763555752,"width":73.98,"height":31}},{"text":"    <div>","targetRectangle":{"y":610.157615707296,"x":69.11188763555752,"width":67.14,"height":31}},{"text":"      …do anything else…","targetRectangle":{"y":641.157615707296,"x":69.11188763555752,"width":199.692,"height":31}},{"text":"    </div>","targetRectangle":{"y":672.157615707296,"x":69.11188763555752,"width":73.98,"height":31}},{"text":"  </li>","targetRectangle":{"y":703.157615707296,"x":69.11188763555752,"width":49.158,"height":31}},{"text":"</ul>","targetRectangle":{"y":734.157615707296,"x":69.11188763555752,"width":45.97199999999999,"height":25}},{"text":"Create a formatItem directive with complex conditions!!","targetRectangle":{"y":411.9931881043916,"x":488.8238634771238,"width":486.2160000000001,"height":66}}],"baseLayer":{"animations":[],"initialState":{"affineTransform":[1,0,0,1,0,0],"masksToBounds":false,"rotation":0,"scale":1,"position":{"pointX":512,"pointY":384},"width":1024,"sublayerTransform":[1,0,0,0,0,1,0,0,0,0,1,0,0,0,0,1],"contentsRect":{"y":0,"x":0,"width":1,"height":1},"opacity":1,"edgeAntialiasingMask":251658240,"height":768,"hidden":false,"anchorPoint":{"pointX":0.5,"pointY":0.5}},"objectID":"0","layers":[{"animations":[],"initialState":{"affineTransform":[1,0,0,1,0,0],"masksToBounds":false,"rotation":0,"scale":1,"position":{"pointX":512,"pointY":384},"width":1024,"sublayerTransform":[1,0,0,0,0,1,0,0,0,0,1,-0.0004922987690640373,0,0,0,1],"contentsRect":{"y":0,"x":0,"width":1,"height":1},"opacity":1,"edgeAntialiasingMask":251658240,"height":768,"hidden":false,"anchorPoint":{"pointX":0.5,"pointY":0.5}},"layers":[{"animations":[],"layers":[],"initialState":{"affineTransform":[1,0,0,1,0,0],"masksToBounds":false,"rotation":0,"scale":1,"position":{"pointX":512,"pointY":384},"width":1024,"sublayerTransform":[1,0,0,0,0,1,0,0,0,0,1,0,0,0,0,1],"contentsRect":{"y":0,"x":0,"width":1,"height":1},"opacity":1,"edgeAntialiasingMask":0,"height":768,"hidden":false,"anchorPoint":{"pointX":0.5,"pointY":0.5}},"texture":"B3B9AA996F79885C6FAB5E6D0A29C9E9"}]}]}}]}